Workbook
Name anscount: 1
Name Bu: [1]INPUT!$B$10
Name DC: [1]INPUT!$B$8
Name EXHIBIT_01: #REF!
Name EXHIBIT_02: #REF!
Name EXHIBIT_02: #REF!
Name EXHIBIT_02: #REF!
Name EXHIBIT_05: #REF!
Name EXHIBIT_05: #REF!
Name EXHIBIT_05: #REF!
Name EXHIBIT_06: #REF!
Name EXHIBIT_06: #REF!
Name EXHIBIT_06: #REF!
Name EXHIBIT_07: #REF!
Name EXHIBIT_07: #REF!
Name EXHIBIT_07: #REF!
Name EXHIBIT_08: #REF!
Name EXHIBIT_08: #REF!
Name EXHIBIT_08: #REF!
Name new_proj: '[2]Novos Projectos'!$A$3:$A$57
Name Pm: [1]INPUT!$B$6
Name Rd: [1]INPUT!$B$4
Name t: [1]INPUT!$B$7
Name TD: [1]INPUT!$B$9
Name VARa: [1]INPUT!$B$12

Sheet CAPA
B1: Modelo Financeiro do Plano de Negócios
B2: IAPMEI
B3: EzPower by Flexible Energies
B4: Data 14/04/2025
B5: Apr.2025

Sheet Regras de Utilização
C1: NOTA: A utilização desta ferramenta, disponibilizada pelo IAPMEI, é completamente autónoma de qualquer outra área/atividade do IAPMEI. Independentemente do fim a que se destine, a utilização da ferramenta, assim como dos resultados com ela obtidos, é da inteira responsabilidade de cada utilizador.
B4: Regras de utilização
B6: Para a melhor utilização do presente modelo, o empreendedor deverá dominar conceitos básicos de análise económica e financeira ou, não sendo esse o caso, deverá explorar as potencialidades do presente modelo acompanhado por alguém conhecedor desses conceitos. Por outro lado, este modelo Económico-Financeiro deverá ser acompanhado de informação qualitativa detalhada sobre o projeto e de explicação dos pressupostos de cálculos efetuados.
B10: Principais regras de utilização:
B12: Ü Só devem ser inseridos valores nas células com fundo branco;
B13: Ü Os valores que se encontrem a azul poderão ser alterados, mas dentro dos mesmos parâmetros;
B14: Ü A utilização deste modelo tem por base um trabalho prévio por parte do utilizador, no que diz respeito à previsão de proveitos e de custos;
B15: Ü No caso de pretender efetuar uma análise de sensibilidade, utilize este mesmo modelo, mas com diferentes valores.
B17: Passos para preenchimento:
B19: 1 | C19: Para que possa tirar partido de todas as funcionalidades do modelo, deverá confirmar se o nível de segurança das Macros está em Médio. Para isso, basta ir às 'Ferramentas' - 'Macro' - 'Segurança' e no Nível de Segurança escolher/confirmar se está no Médio. Caso não esteja, coloque a opção já indicada e feche o ficheiro. Quando reabrir, selecione 'Aceitar Macro'.
B21: 2 | C21: Colocar o nome da empresa na célula E1 na sheet de Pressupostos.
B23: 3 | C23: Estimar o volume de negócios da empresa, através das quantidades vendidas, preço de venda dos produtos e de prestação de serviços. Caso pretenda, utilize a folha de cálculo anexa e faça apenas as respetivas ligações, de acordo com a classificação contabilística do seu volume de negócios.
B25: 4 | C25: Colocar na sheet CMVMC, na célula correspondente, as margens brutas de negócio para cada um dos produtos vendidos.
B27: 5 | C27: Na sheet FSE, estimar um valor médio mensal para cada umas das rubricas que se adaptem à empresa/negócio.
B29: 6 | C29: Na sheet Gastos com Pessoal, definir os colaboradores (Gerência e Pessoal) da empresa e respetivas remunerações brutas mensais. Para além disto, definir, caso se aplique, um valor para a formação e outros custos com pessoal.
B31: 7 | C31: Posteriormente, definir o quadro de investimento da empresa/projeto na sheet de Investimentos, repartida pelas diferentes rubricas de investimento em ativo fixo.
B33: 8 | C33: Na sheet de Fundo Maneio, definir a Reserva de Segurança de Tesouraria. Esta rubrica representa um valor mínimo de disponibilidades a manter ao longo do projeto.
B35: 9 | C35: Após a definição de todos estes pressupostos, tem que definir a forma de financiamento do projeto na sheet Financiamento. Deverá indicar o valor de capital social inicial e eventuais aumentos, bem como o nível de suprimentos da empresa e/ou o valor dos empréstimos bancários.
B37: 10 | C37: Os inputs do modelo estão inseridos, sendo necessário apenas fazer o acerto de disponibilidades. Assim sendo, na sheet de Plano Financeiro, carregar no retângulo que indica 'Acerto do modelo'.
B39: 11 | C39: No caso de pretender considerar um número superior de produtos ou serviços do que os previstos na sheet VN, recomenda-se: a) Copiar a sheet VN para uma folha desprotegida, em que poderá considerar todos os produtos; b) Colocar o valor total dos produtos para o mercado interno em VN - Produto A, e o valor total de produtos exportados em Exportações - Produto A.
B41: 12 | C41: Aconselha-se considerar as Imparidades em 0%, pelas implicações a nível de interpretação, já que apenas serão contabilizadas imparidades sobre Clientes com consequência no valor do Fundo de Maneio.
... B49: 16 | C49: Acertar Modelo: Após carregamento dos dados e sempre que introduza alterações, é necessário carregar na função 'Acertar Modelo' na sheet Plano Financeiro. Se necessário, carregar 2 vezes em 'Acertar Modelo'.
B51: NOTA | C51: No caso de empresas industriais, é aconselhado o uso da sheet Cálculos Auxiliares. Esta sheet constitui uma base de cálculo indispensável ao suporte previsional do modelo de projeções.

Sheet Pressupostos
D1: Empresa: | E1: XFCP Lda
A4: Pressupostos Gerais
A6: Valide os pressupostos aqui indicados e ajuste-os de acordo com o seu projeto
A9: Unidade Monetária | B9: Euros
A11: Ano Inicial do Projeto (Ano 0) | B11: 2019 | C11: = ano em que inicia o investimento e poderá ou não haver exploração
A12: Início da Produção ano/meses de produção (DEPRECIAÇÕES) | B12: Folha Investimento - Linha 31 | C12: Meses
A13: Prazo Médio de Recebimento (dias) / (meses) | B13: 60 | C13: =+B13/30 | D13: A definir em função da prática da empresa e do setor, assim como da política a prosseguir.
A14: Prazo Médio de Pagamento (dias) / (meses) | B14: 30 | C14: =+B14/30
A15: Prazo Médio de Stockagem (dias) / (meses) | B15: 60 | C15: =+B15/30
A16: Prazo de Pagamento de IVA (trim = 4; mensal =12) | B16: 1 | C16: =+B16 | D16: 4 = trim; 12 = mensal
A18: Taxa de IVA - Vendas | B18: 0.23 | C18: Em função do tipo de produtos e serviços
A19: Taxa de IVA - Prestação Serviços | B19: 0.23
A20: Taxa de IVA - CMVMC | B20: 0.23
A21: Taxa de IVA - FSE | B21: 0.23
A22: Taxa de IVA - Investimento | B22: 0.23
A24: Taxa de Segurança Social - Entidade - Órgãos Sociais | B24: 0.2375 | C24: Em vigor no ano base
A25: Taxa de Segurança Social - Entidade - Colaboradores | B25: 0.2375
A26: Taxa de Segurança Social - Pessoal - Órgãos Sociais | B26: 0.11
A27: Taxa de Segurança Social - Pessoal - Colaboradores | B27: 0.11
A28: Taxa Média de IRS | B28: 0.15 | C28: A definir em função da Lei e do valor dos rendimentos do trabalho.
A29: Taxa de IRC | B29: 0.21 | C29: Definido por Lei - ter em conta a localização e condições específicas da atividade.
A31: Taxa de Aplicações Financeiras Curto Prazo | B31: 0.005 | C31: Ver condições de mercado e risco da empresa na ótica bancária.
A32: Taxa de Juro de Empréstimo Curto Prazo | B32: 0
A33: Taxa de Juro de Empréstimo ML Prazo | B33: 0
A35: Taxa de Juro de Ativos Sem Risco - Rf (Obrig.Tesouro) | C35: NOTA: Quando não se aplica Beta, colocar:
A36: Prémio de Risco de Mercado = (Rm*-Rf) ** | C36: Um valor para o prémio de risco (pº) adequado ao projeto
A37: Beta U a partir de BL de Empresa(s) de Referência | B37: 1 | C37: Beta = 100% se não utilizar Beta (não utilizar BL de empresa de referência)
A38: Taxa de Crescimento dos Cash Flows na Perpetuidade | B38: 0.0001 | C38: Na maioria dos projetos, considerar 0% e utilizar não a perpetuidade mas sim o valor residual = valor do Ativo Fixo não Amortizado e o Valor Residual do F. Maneio no último ano. Na folha 'Avaliação' existem as 2 hipóteses.
A39: * Rm - Rendimento esperado de mercado (entenda-se mercado acionista de referência)
A40: ** Em Portugal 2019 será razoável em investimentos "normais" 6% a 8%
A43: Metodologias de avaliação | B43: (Para ver, abrir linha 44 até final do texto, com 2 clicks na célula)
A44: O método dos fluxos de caixa descontados consiste em estimar os fluxos de caixa futuros do projeto e atualizá-los para o momento de avaliação, utilizando uma taxa de desconto (= taxa de atualização = custo do capital desejado pelo investidor) adequada em função do risco do projeto. O Beta B obtido duma empresa de referência (ou mais do que uma) cotada em Bolsa (pode ser a própria empresa que vai implementar o projeto) exprime o risco relativo da empresa em relação ao risco global de mercado - diz-se Beta da ação = relação de variação entre a cotação da empresa e a variação do Índice de mercado. Bação = Covar(Rendibilid do Título;Rendibilid de mercado) / Var (Rendibilidade de mercado) Free Cash Flow to da Firm βL pode ser <,= ou > 1, sendo o risco tamto maior quanto maior for BL. O Beta assim obtido diz-se alavancado BL pelo que importa eliminar o efeito de alavancagem do Capital Alheio da empresa e obter asso o Beta deslavancado dito BU, para utilizar na avaliação de projetos BL = BU x [1 + (1-ti) x (CA /CP)] => BU = BL / [1 + (1-ti) x (CA /CP)] em que : CA (ou P) - capital alheio; CP - Capital Prório e ti - tx de imposto (irc) AVALIAÇÃO DO PROJETO - Calculam-se os Cash Flows Líquidos FCFF = CFL = EBITx(1-t)+Amortiz - Investimento (Capital Fixo - Fundo de Maneio Necessário) + valor residual investim. (ano n) - Determina-se a Taxa de atualização (desconto, custo de capital) adequada à ótica de avaliação considerada 1. Avaliação na ótica do investimento (pré-financiamento) ignora a forma de financiamento o que equivale a = 100% Cap Próprio) A Taxa de atualização (desconto) = re = Rf + Bu*(Rm - Rf). 2. Avaliação na Ótica do Investiemnto pós-financiamento, incorpora os efeitos do capital alheio refletidos na taxa de utilização Taxa de atualização = wacc (custo médio ponderado do capital) = Rcp*CP /(CP+CA)+ Rca*(1-ti)*CA/ (CP+CA) com Rcp = re = Rf + Bu*(Rm-Rf) e Rca - taxa de juro efetiva do capital alheio Em alternativa, pode utilizar-se método considerando Rcp = Rf + Bp*(Rm-Rf). com Bp = Bu*(1+(1-ti)*(CA/CP)) com CA e CP do projeto 3. Avaliação na Ótica do Investidor (ou do Capital Próprio) (Free Cash Flow to Equity) No método de avaliação pelo desconto de fluxos de caixa líquido do acionista (FCFE - Free Cashflow to Equity), o objetivo é avaliar diretamente o valor líquido e a remuneração do capital do investidor (ou do acionista da empresa) Os Cash Flows (FCFE) = Cash flows na ótica do Investimento + Cash Flows de financiamento em cada ano FCFEt = Resultado operacional*(1-ti) + Amortizações Inv - Investimento (cap. fixo e fundo de maneio) + Financiamento obtido - reeembolsos de financiamento - Encargos financeiros*(1-ti) - taxa de atualização = Rcp (CAPM) = Rf + Bu*(Rm - Rf). NOTAS: 1. Em todos os métodos, considera-se o Valor Residual dos CASH FLOWS no último ano, que podem influenciar significativamente, consoante o método de cálculo, o Valor dos indicadores (VAL e TIR). 2. É usual utilizar a taxa de atualização do 1º ano em todos os períodos - O que não acontece nesta Folha calc que altera a tx atualização em cada ano

Sheet VN
G1: Empresa: | H1: =+Pressupostos!E1
A2: s | H2: =+Pressupostos!B9
A4: Vendas + Prestações de Serviços
C8: =+Pressupostos!B11 | D8: =+C8+1 | E8: =+D8+1 | F8: =+E8+1 | G8: =+F8+1 | H8: =+G8+1
A9: Taxa de Variação dos Preços
A12: VENDAS - MERCADO NACIONAL | C12: =+C8 | D12: =+D8 | E12: =+E8 | F12: =+F8 | G12: =+G8 | H12: =+H8
A13: Produto A | C13: =+C16*C14 | D13: =+D16*D14 | E13: =+E16*E14 | F13: =+F16*F14 | G13: =+G16*G14 | H13: =+H16*H14
A14: Quantidades Vendidas | D14: =+C14*(1+D15) | E14: =+D14*(1+E15) | F14: =+E14*(1+F15) | G14: =+F14*(1+G15) | H14: =+G14*(1+H15)
A15: Taxa de Crescimento das Unidades Vendidas
A16: Preço Unitário | D16: =+C16*(1+D9) | E16: =+D16*(1+E9) | F16: =+E16*(1+F9) | G16: =+F16*(1+G9) | H16: =+G16*(1+H9)
A17: Produto B | C17: =+C20*C18 | D17: =+D20*D18 | E17: =+E20*E18 | F17: =+F20*F18 | G17: =+G20*G18 | H17: =+H20*H18
A18: Quantidades Vendidas | D18: =+C18*(1+D19) | E18: =+D18*(1+E19) | F18: =+E18*(1+F19) | G18: =+F18*(1+G19) | H18: =+G18*(1+H19)
A19: Taxa de Crescimento das Unidades Vendidas
A20: Preço Unitário | D20: =+C20*(1+D9) | E20: =+D20*(1+E9) | F20: =+E20*(1+F9) | G20: =+F20*(1+G9) | H20: =+G20*(1+H9)
A21: Produto C * | C21: =+C24*C22 | D21: =+D24*D22 | E21: =+E24*E22 | F21: =+F24*F22 | G21: =+G24*G22 | H21: =+H24*H22
A22: Quantidades Vendidas | D22: =+C22*(1+D23) | E22: =+D22*(1+E23) | F22: =+E22*(1+F23) | G22: =+F22*(1+G23) | H22: =+G22*(1+H23)
A23: Taxa de Crescimento das Unidades Vendidas
A24: Preço Unitário | D24: =+C24*(1+D9) | E24: =+D24*(1+E9) | F24: =+E24*(1+F9) | G24: =+F24*(1+G9) | H24: =+G24*(1+H9)
A25: Produto D * | C25: =+C28*C26 | D25: =+D28*D26 | E25: =+E28*E26 | F25: =+F28*F26 | G25: =+G28*G26 | H25: =+H28*H26
A26: Quantidades Vendidas | D26: =+C26*(1+D27) | E26: =+D26*(1+E27) | F26: =+E26*(1+F27) | G26: =+F26*(1+G27) | H26: =+G26*(1+H27)
A27: Taxa de Crescimento das Unidades Vendidas
A28: Preço Unitário | D28: =+C28*(1+D9) | E28: =+D28*(1+E9) | F28: =+E28*(1+F9) | G28: =+F28*(1+G9) | H28: =+G28*(1+H9)
A29: TOTAL | C29: =+C13+C17+C21+C25 | D29: =+D13+D17+D21+D25 | E29: =+E13+E17+E21+E25 | F29: =+F13+F17+F21+F25 | G29: =+G13+G17+G21+G25 | H29: =+H13+H17+H21+H25
A32: VENDAS - EXPORTAÇÃO | C32: =+C8 | D32: =+D8 | E32: =+E8 | F32: =+F8 | G32: =+G8 | H32: =+H8
A33: =A13 | C33: =+C36*C34 | D33: =+D36*D34 | E33: =+E36*E34 | F33: =+F36*F34 | G33: =+G36*G34 | H33: =+H36*H34
A34: Quantidades Vendidas | D34: =+C34*(1+D35) | E34: =+D34*(1+E35) | F34: =+E34*(1+F35) | G34: =+F34*(1+G35) | H34: =+G34*(1+H35)
A35: Taxa de Crescimento das Unidades Vendidas
A36: Preço Unitário | D36: =+C36*(1+D9) | E36: =+D36*(1+E9) | F36: =+E36*(1+F9) | G36: =+F36*(1+G9) | H36: =+G36*(1+H9)
A37: =A17 | C37: =+C40*C38 | D37: =+D40*D38 | E37: =+E40*E38 | F37: =+F40*F38 | G37: =+G40*G38 | H37: =+H40*H38
A38: Quantidades Vendidas | D38: =+C38*(1+D39) | E38: =+D38*(1+E39) | F38: =+E38*(1+F39) | G38: =+F38*(1+G39) | H38: =+G38*(1+H39)
A39: Taxa de Crescimento das Unidades Vendidas
A40: Preço Unitário | D40: =+C40*(1+D9) | E40: =+D40*(1+E9) | F40: =+E40*(1+F9) | G40: =+F40*(1+G9) | H40: =+G40*(1+H9)
A41: TOTAL | C41: =+C33+C37 | D41: =+D33+D37 | E41: =+E33+E37 | F41: =+F33+F37 | G41: =+G33+G37 | H41: =+H33+H37
A42: * Produtos / Famílias de Produtos / Mercadorias
A43: NOTA: Caso não tenha conhecimento das quantidades, colocar o valor das vendas na linha das 'Quantidades Vendidas' e o valor 1 na linha do 'Preço Unitário'.
A45: PRESTAÇÕES DE SERVIÇOS - MERCADO NACIONAL | C45: =+C8 | D45: =+D8 | E45: =+E8 | F45: =+F8 | G45: =+G8 | H45: =+H8
A46: Estudos | D46: =+C46*(1+D47) | E46: =+D46*(1+E47) | F46: =+E46*(1+F47) | G46: =+F46*(1+G47) | H46: =+G46*(1+H47)
A47: Taxa de Crescimento
A48: Contratos de Consultoria e Assistência Técnica
A49: Taxa de Crescimento
A50: Serviços Diversos Não Especificados | D50: =+C50*(1+D51) | E50: =+D50*(1+E51) | F50: =+E50*(1+F51) | G50: =+F50*(1+G51) | H50: =+G50*(1+H51)
A51: Taxa de Crescimento
A52: Outros Serviços Diversos Não Especificados | D52: =+C52*(1+D53) | E52: =+D52*(1+E53) | F52: =+E52*(1+F53) | G52: =+F52*(1+G53) | H52: =+G52*(1+H53)
A53: Taxa de Crescimento
A54: TOTAL | C54: =+C46+C48+C50+C52 | D54: =+D46+D48+D50+D52 | E54: =+E46+E48+E50+E52 | F54: =+F46+F48+F50+F52 | G54: =+G46+G48+G50+G52 | H54: =+H46+H48+H50+H52
A57: PRESTAÇÕES DE SERVIÇOS - EXPORTAÇÕES | C57: =+C8 | D57: =+D8 | E57: =+E8 | F57: =+F8 | G57: =+G8 | H57: =+H8
A58: =A46
A59: Taxa de Crescimento
A60: =A48 | D60: =+C60*(1+D61) | E60: =+D60*(1+E61) | F60: =+E60*(1+F61) | G60: =+F60*(1+G61) | H60: =+G60*(1+H61)
A61: Taxa de Crescimento
A62: =A50 | D62: =+C62*(1+D63) | E62: =+D62*(1+E63) | F62: =+E62*(1+F63) | G62: =+F62*(1+G63) | H62: =+G62*(1+H63)
A63: Taxa de Crescimento
A64: =A52 | D64: =+C64*(1+D65) | E64: =+D64*(1+E65) | F64: =+E64*(1+F65) | G64: =+F64*(1+G65) | H64: =+G64*(1+H65)
A65: Taxa de Crescimento
A66: TOTAL | C66: =+C58+C60+C62+C64 | D66: =+D58+D60+D62+D64 | E66: =+E58+E60+E62+E64 | F66: =+F58+F60+F62+F64 | G66: =+G58+G60+G62+G64 | H66: =+H58+H60+H62+H64
A69: TOTAL VENDAS - MERCADO NACIONAL | C69: =+C29 | D69: =+D29 | E69: =+E29 | F69: =+F29 | G69: =+G29 | H69: =+H29
A70: TOTAL VENDAS - EXPORTAÇÕES | C70: =+C41 | D70: =+D41 | E70: =+E41 | F70: =+F41 | G70: =+G41 | H70: =+H41
A71: TOTAL VENDAS | C71: =+C69+C70 | D71: =+D69+D70 | E71: =+E69+E70 | F71: =+F69+F70 | G71: =+G69+G70 | H71: =+H69+H70
A72: IVA VENDAS | B72: =+Pressupostos!B18 | C72: =+C69*$B$72 | D72: =+D69*$B$72 | E72: =+E69*$B$72 | F72: =+F69*$B$72 | G72: =+G69*$B$72 | H72: =+H69*$B$72
A75: TOTAL PRESTAÇÕES DE SERVIÇOS - MERCADO NACIONAL | C75: =+C54 | D75: =+D54 | E75: =+E54 | F75: =+F54 | G75: =+G54 | H75: =+H54
A76: TOTAL PRESTAÇÕES DE SERVIÇOS - EXPORTAÇÕES | C76: =+C66 | D76: =+D66 | E76: =+E66 | F76: =+F66 | G76: =+G66 | H76: =+H66
A77: TOTAL PRESTAÇÕES SERVIÇOS | C77: =+C75+C76 | D77: =+D75+D76 | E77: =+E75+E76 | F77: =+F75+F76 | G77: =+G75+G76 | H77: =+H75+H76
A78: IVA PRESTAÇÕES DE SERVIÇOS | B78: =+Pressupostos!B19 | C78: =+C75*$B$78 | D78: =+D75*$B$78 | E78: =+E75*$B$78 | F78: =+F75*$B$78 | G78: =+G75*$B$78 | H78: =+H75*$B$78
A80: TOTAL VOLUME DE NEGÓCIOS | C80: =+C71+C77 | D80: =+D71+D77 | E80: =+E71+E77 | F80: =+F71+F77 | G80: =+G71+G77 | H80: =+H71+H77
A82: IVA | C82: =+C72+C78 | D82: =+D72+D78 | E82: =+E72+E78 | F82: =+F72+F78 | G82: =+G72+G78 | H82: =+H72+H78
A84: TOTAL VOLUME DE NEGÓCIOS + IVA | C84: =+C80+C82 | D84: =+D80+D82 | E84: =+E80+E82 | F84: =+F80+F82 | G84: =+G80+G82 | H84: =+H80+H82
A87: Perdas por Imparidade % | B87: 0 | C87: =+$B$87*C84 | D87: =+$B$87*D84 | E87: =+$B$87*E84 | F87: =+$B$87*F84 | G87: =+$B$87*G84 | H87: =+$B$87*H84

Sheet CMVMC
G1: EMPRESA: | H1: =+Pressupostos!E1
H2: =+Pressupostos!B9
A4: CMVMC - Custo das Mercadorias Vendidas e Matérias Consumidas
A7: CMVMC | B7: Margem Bruta % | C7: =+VN!C8 | D7: =+VN!D8 | E7: =+VN!E8 | F7: =+VN!F8 | G7: =+VN!G8 | H7: =+VN!H8
A8: MERCADO NACIONAL | C8: =+SUM(C9:C12) | D8: =+SUM(D9:D12) | E8: =+SUM(E9:E12) | F8: =+SUM(F9:F12) | G8: =+SUM(G9:G12) | H8: =+SUM(H9:H12)
A9: =+VN!A13 | C9: =VN!C13*(1-CMVMC!$B$9) | D9: =VN!D13*(1-CMVMC!$B$9) | E9: =VN!E13*(1-CMVMC!$B$9) | F9: =VN!F13*(1-CMVMC!$B$9) | G9: =VN!G13*(1-CMVMC!$B$9) | H9: =VN!H13*(1-CMVMC!$B$9)
A10: =+VN!A17 | C10: =VN!C17*(1-CMVMC!$B$10) | D10: =VN!D17*(1-CMVMC!$B$10) | E10: =VN!E17*(1-CMVMC!$B$10) | F10: =VN!F17*(1-CMVMC!$B$10) | G10: =VN!G17*(1-CMVMC!$B$10) | H10: =VN!H17*(1-CMVMC!$B$10)
A11: =+VN!A21 | C11: =VN!C21*(1-CMVMC!$B$11) | D11: =VN!D21*(1-CMVMC!$B$11) | E11: =VN!E21*(1-CMVMC!$B$11) | F11: =VN!F21*(1-CMVMC!$B$11) | G11: =VN!G21*(1-CMVMC!$B$11) | H11: =VN!H21*(1-CMVMC!$B$11)
A12: =+VN!A25 | C12: =VN!C25*(1-CMVMC!$B$12) | D12: =VN!D25*(1-CMVMC!$B$12) | E12: =VN!E25*(1-CMVMC!$B$12) | F12: =VN!F25*(1-CMVMC!$B$12) | G12: =VN!G25*(1-CMVMC!$B$12) | H12: =VN!H25*(1-CMVMC!$B$12)
A13: MERCADO EXTERNO | C13: =+C15+C14 | D13: =+D15+D14 | E13: =+E15+E14 | F13: =+F15+F14 | G13: =+G15+G14 | H13: =+H15+H14
A14: =+VN!A33 | C14: =VN!C33*(1-CMVMC!$B$14) | D14: =VN!D33*(1-CMVMC!$B$14) | E14: =VN!E33*(1-CMVMC!$B$14) | F14: =VN!F33*(1-CMVMC!$B$14) | G14: =VN!G33*(1-CMVMC!$B$14) | H14: =VN!H33*(1-CMVMC!$B$14)
A15: =+VN!A37 | C15: =VN!C37*(1-CMVMC!$B$15) | D15: =VN!D37*(1-CMVMC!$B$15) | E15: =VN!E37*(1-CMVMC!$B$15) | F15: =VN!F37*(1-CMVMC!$B$15) | G15: =VN!G37*(1-CMVMC!$B$15) | H15: =VN!H37*(1-CMVMC!$B$15)
A16: TOTAL CMVMC | C16: =+C8+C13 | D16: =+D8+D13 | E16: =+E8+E13 | F16: =+F8+F13 | G16: =+G8+G13 | H16: =+H8+H13
A18: IVA | B18: =+Pressupostos!B20 | C18: =+C8*$B$18 | D18: =+D8*$B$18 | E18: =+E8*$B$18 | F18: =+F8*$B$18 | G18: =+G8*$B$18 | H18: =+H8*$B$18
A20: TOTAL CMVMC + IVA | C20: =+C16+C18 | D20: =+D16+D18 | E20: =+E16+E18 | F20: =+F16+F18 | G20: =+G16+G18 | H20: =+H16+H18
A23: NOTA 1: Mapa construído caso a caso:
A24: a) Introduzir a Margem Bruta diretamente, quando conhecida e passível de ser utilizada, ou efetuar a respetiva fórmula de cálculo;
A25: b) Efetuar os cálculos auxiliares considerados necessários para alcançar o nível de matéria-prima por unidade produzida e introduzir manualmente os valores;
A26: c) Caso não seja possível alcançar o nível do consumo de matéria-prima por produto, introduzir o valor do custo total, após a realização dos respetivos cálculos auxiliares.
A28: NOTA 2: Está disponível uma folha para cálculos auxiliares. Contém mapas para cálculo do CMVMC de projetos industriais.

Sheet FSE
J1: =+VN!G1 | K1: =+Pressupostos!E1
K2: =+Pressupostos!B9
A4: FSE - Fornecimentos e Serviços Externos
F7: =+VN!C8 | G7: =+VN!D8 | H7: =+VN!E8 | I7: =+VN!F8 | J7: =+VN!G8 | K7: =+VN!H8
A8: N.º Meses de produção | F8: 12 | G8: 12 | H8: 12 | I8: 12 | J8: 12 | K8: 12
A9: Taxa de Crescimento % | F9: 0
B12: Tx IVA | C12: CF % | D12: CV % | E12: Valor Mensal | F12: =+VN!C8 | G12: =+VN!D8 | H12: =+VN!E8 | I12: =+VN!F8 | J12: =+VN!G8 | K12: =+VN!H8
A13: Subcontratos | B13: =Pressupostos!$B$21 | C13: =100%-D13 | F13: =E13*$F$8 | G13: =+E13*$G$8*(1+$G$9) | H13: =+E13*(1+$G$9)*(1+$H$9)*H$8 | I13: =+H13*(1+I$9) | J13: =+I13*(1+J$9) | K13: =+J13*(1+K$9)
A14: Serviços Especializados
A15: Trabalhos Especializados | B15: =Pressupostos!$B$21 | C15: =100%-D15 | F15: =E15*$F$8 | G15: =+E15*$G$8*(1+$G$9) | H15: =+E15*(1+$G$9)*(1+$H$9)*H$8 | I15: =+H15*(1+I$9) | J15: =+I15*(1+J$9) | K15: =+J15*(1+K$9)
A16: Publicidade e Propaganda | B16: =Pressupostos!$B$21 | C16: =100%-D16 | F16: =E16*$F$8 | G16: =+E16*$G$8*(1+$G$9) | H16: =+E16*(1+$G$9)*(1+$H$9)*H$8 | I16: =+H16*(1+I$9) | J16: =+I16*(1+J$9) | K16: =+J16*(1+K$9)
A17: Vigilância e Segurança | B17: =Pressupostos!$B$21 | C17: =100%-D17 | F17: =E17*$F$8 | G17: =G19 | H17: =+E17*(1+$G$9)*(1+$H$9)*H$8 | I17: =+H17*(1+I$9) | J17: =+I17*(1+J$9) | K17: =+J17*(1+K$9)
A18: Honorários | B18: =Pressupostos!$B$21 | C18: =100%-D18 | F18: =E18*$F$8 | G18: =+E18*$G$8*(1+$G$9) | H18: =+E18*(1+$G$9)*(1+$H$9)*H$8 | I18: =+H18*(1+I$9) | J18: =+I18*(1+J$9) | K18: =+J18*(1+K$9)
A19: Comissões | B19: =Pressupostos!$B$21 | C19: =100%-D19 | F19: =E19*$F$8 | G19: =+E19*$G$8*(1+$G$9) | H19: =+E19*(1+$G$9)*(1+$H$9)*H$8 | I19: =+H19*(1+I$9) | J19: =+I19*(1+J$9) | K19: =+J19*(1+K$9)
A20: Conservação e Reparação | B20: =Pressupostos!$B$21 | C20: =100%-D20 | F20: =E20*$F$8 | G20: =+E20*$G$8*(1+$G$9) | H20: =+E20*(1+$G$9)*(1+$H$9)*H$8 | I20: =+H20*(1+I$9) | J20: =+I20*(1+J$9) | K20: =+J20*(1+K$9)
A21: Materiais
A22: Ferramentas e Utensílios de Desgaste Rápido | B22: =Pressupostos!$B$21 | C22: =100%-D22 | F22: =E22*$F$8 | G22: =+E22*$G$8*(1+$G$9) | H22: =+E22*(1+$G$9)*(1+$H$9)*H$8 | I22: =+H22*(1+I$9) | J22: =+I22*(1+J$9) | K22: =+J22*(1+K$9)
A23: Livros e Documentação Técnica | B23: =Pressupostos!$B$21 | C23: =100%-D23 | F23: =E23*$F$8 | G23: =+E23*$G$8*(1+$G$9) | H23: =+E23*(1+$G$9)*(1+$H$9)*H$8 | I23: =+H23*(1+I$9) | J23: =+I23*(1+J$9) | K23: =+J23*(1+K$9)
A24: Material de Escritório | B24: =Pressupostos!$B$21 | C24: =100%-D24 | F24: =E24*$F$8 | G24: =+E24*$G$8*(1+$G$9) | H24: =+E24*(1+$G$9)*(1+$H$9)*H$8 | I24: =+H24*(1+I$9) | J24: =+I24*(1+J$9) | K24: =+J24*(1+K$9)
A25: Artigos para Oferta | B25: =Pressupostos!$B$21 | C25: =100%-D25 | F25: =E25*$F$8 | G25: =+E25*$G$8*(1+$G$9) | H25: =+E25*(1+$G$9)*(1+$H$9)*H$8 | I25: =+H25*(1+I$9) | J25: =+I25*(1+J$9) | K25: =+J25*(1+K$9)
A26: Energia e Fluidos
A27: Eletricidade | B27: =Pressupostos!$B$21 | C27: =100%-D27 | F27: =E27*$F$8 | G27: =+E27*$G$8*(1+$G$9) | H27: =+E27*(1+$G$9)*(1+$H$9)*H$8 | I27: =+H27*(1+I$9) | J27: =+I27*(1+J$9) | K27: =+J27*(1+K$9)
A28: Combustíveis | B28: =Pressupostos!$B$21 | C28: =100%-D28 | F28: =E28*$F$8 | G28: =+E28*$G$8*(1+$G$9) | H28: =+E28*(1+$G$9)*(1+$H$9)*H$8 | I28: =+H28*(1+I$9) | J28: =+I28*(1+J$9) | K28: =+J28*(1+K$9)
A29: Água | B29: 0.06 | C29: =100%-D29 | F29: =E29*$F$8 | G29: =+E29*$G$8*(1+$G$9) | H29: =+E29*(1+$G$9)*(1+$H$9)*H$8 | I29: =+H29*(1+I$9) | J29: =+I29*(1+J$9) | K29: =+J29*(1+K$9)
A30: Deslocações, Estadas e Transportes
A31: Deslocações e Estadas | B31: =Pressupostos!$B$21 | C31: =100%-D31 | F31: =E31*$F$8 | G31: =+E31*$G$8*(1+$G$9) | H31: =+E31*(1+$G$9)*(1+$H$9)*H$8 | I31: =+H31*(1+I$9) | J31: =+I31*(1+J$9) | K31: =+J31*(1+K$9)
A32: Transportes de Pessoal | B32: =Pressupostos!$B$21 | C32: =100%-D32 | F32: =E32*$F$8 | G32: =+E32*$G$8*(1+$G$9) | H32: =+E32*(1+$G$9)*(1+$H$9)*H$8 | I32: =+H32*(1+I$9) | J32: =+I32*(1+J$9) | K32: =+J32*(1+K$9)
A33: Transportes de Mercadorias | B33: =Pressupostos!$B$21 | C33: =100%-D33 | F33: =E33*$F$8 | G33: =+E33*$G$8*(1+$G$9) | H33: =+E33*(1+$G$9)*(1+$H$9)*H$8 | I33: =+H33*(1+I$9) | J33: =+I33*(1+J$9) | K33: =+J33*(1+K$9)
A34: Serviços Diversos
A35: Rendas e Alugueres | B35: =Pressupostos!$B$21 | C35: =100%-D35 | F35: =E35*$F$8 | G35: =+E35*$G$8*(1+$G$9) | H35: 0 | I35: =+H35*(1+I$9) | J35: =+I35*(1+J$9) | K35: =+J35*(1+K$9)
A36: Comunicação | B36: =Pressupostos!$B$21 | C36: =100%-D36 | F36: =E36*$F$8 | G36: =+E36*$G$8*(1+$G$9) | H36: =+E36*(1+$G$9)*(1+$H$9)*H$8 | I36: =+H36*(1+I$9) | J36: =+I36*(1+J$9) | K36: =+J36*(1+K$9)
A37: Seguros | B37: 0 | C37: =100%-D37 | F37: =E37*$F$8 | G37: =+E37*$G$8*(1+$G$9) | H37: =+E37*(1+$G$9)*(1+$H$9)*H$8 | I37: =+H37*(1+I$9) | J37: =+I37*(1+J$9) | K37: =+J37*(1+K$9)
A38: Royalties | B38: =Pressupostos!$B$21 | C38: =100%-D38 | F38: =E38*$F$8 | G38: =+E38*$G$8*(1+$G$9) | H38: =+E38*(1+$G$9)*(1+$H$9)*H$8 | I38: =+H38*(1+I$9) | J38: =+I38*(1+J$9) | K38: =+J38*(1+K$9)
A39: Contencioso e Notariado | B39: =Pressupostos!$B$21 | C39: =100%-D39 | F39: =E39*$F$8 | G39: =+E39*$G$8*(1+$G$9) | H39: =+E39*(1+$G$9)*(1+$H$9)*H$8 | I39: =+H39*(1+I$9) | J39: =+I39*(1+J$9) | K39: =+J39*(1+K$9)
A40: Despesas de Representação | B40: =Pressupostos!$B$21 | C40: =100%-D40 | F40: =E40*$F$8 | G40: =+E40*$G$8*(1+$G$9) | H40: =+E40*(1+$G$9)*(1+$H$9)*H$8 | I40: =+H40*(1+I$9) | J40: =+I40*(1+J$9) | K40: =+J40*(1+K$9)
A41: Limpeza, Higiene e Conforto | B41: =Pressupostos!$B$21 | C41: =100%-D41 | F41: =E41*$F$8 | G41: =+E41*$G$8*(1+$G$9) | H41: =+E41*(1+$G$9)*(1+$H$9)*H$8 | I41: =+H41*(1+I$9) | J41: =+I41*(1+J$9) | K41: =+J41*(1+K$9)
A42: Outros Serviços | B42: =Pressupostos!$B$21 | C42: =100%-D42 | F42: =E42*$F$8 | G42: =+E42*$G$8*(1+$G$9) | H42: =+E42*(1+$G$9)*(1+$H$9)*H$8 | I42: =+H42*(1+I$9) | J42: =+I42*(1+J$9) | K42: =+J42*(1+K$9)
A43: TOTAL FSE | F43: =SUM(F13:F42) | G43: =SUM(G13:G42) | H43: =SUM(H13:H42) | I43: =SUM(I13:I42) | J43: =SUM(J13:J42) | K43: =SUM(K13:K42)
A45: FSE - Custos Fixos | F45: =(F13*$C$13)+(F15*$C$15)+(F16*$C$16)+(F17*$C$17)+(F18*$C$18)+(F19*$C$19)+(F20*$C$20)+(F22*$C$22)+(F23*$C$23)+(F24*$C$24)+(F25*$C$25)+(F27*$C$27)+(F28*$C$28)+(F29*$C$29)+(F31*$C$31)+(F32*$C$32)+(F33*$C$33)+(F35*$C$35)+(F36*$C$36)+(F37*$C$37)+(F38*$C$38)+(F39*$C$39)+(F40*$C$40)+(F41*$C$41)+(F42*$C$42) | G45: =(G13*$C$13)+(G15*$C$15)+(G16*$C$16)+(G17*$C$17)+(G18*$C$18)+(G19*$C$19)+(G20*$C$20)+(G22*$C$22)+(G23*$C$23)+(G24*$C$24)+(G25*$C$25)+(G27*$C$27)+(G28*$C$28)+(G29*$C$29)+(G31*$C$31)+(G32*$C$32)+(G33*$C$33)+(G35*$C$35)+(G36*$C$36)+(G37*$C$37)+(G38*$C$38)+(G39*$C$39)+(G40*$C$40)+(G41*$C$41)+(G42*$C$42) | H45: =(H13*$C$13)+(H15*$C$15)+(H16*$C$16)+(H17*$C$17)+(H18*$C$18)+(H19*$C$19)+(H20*$C$20)+(H22*$C$22)+(H23*$C$23)+(H24*$C$24)+(H25*$C$25)+(H27*$C$27)+(H28*$C$28)+(H29*$C$29)+(H31*$C$31)+(H32*$C$32)+(H33*$C$33)+(H35*$C$35)+(H36*$C$36)+(H37*$C$37)+(H38*$C$38)+(H39*$C$39)+(H40*$C$40)+(H41*$C$41)+(H42*$C$42) | I45: =(I13*$C$13)+(I15*$C$15)+(I16*$C$16)+(I17*$C$17)+(I18*$C$18)+(I19*$C$19)+(I20*$C$20)+(I22*$C$22)+(I23*$C$23)+(I24*$C$24)+(I25*$C$25)+(I27*$C$27)+(I28*$C$28)+(I29*$C$29)+(I31*$C$31)+(I32*$C$32)+(I33*$C$33)+(I35*$C$35)+(I36*$C$36)+(I37*$C$37)+(I38*$C$38)+(I39*$C$39)+(I40*$C$40)+(I41*$C$41)+(I42*$C$42) | J45: =(J13*$C$13)+(J15*$C$15)+(J16*$C$16)+(J17*$C$17)+(J18*$C$18)+(J19*$C$19)+(J20*$C$20)+(J22*$C$22)+(J23*$C$23)+(J24*$C$24)+(J25*$C$25)+(J27*$C$27)+(J28*$C$28)+(J29*$C$29)+(J31*$C$31)+(J32*$C$32)+(J33*$C$33)+(J35*$C$35)+(J36*$C$36)+(J37*$C$37)+(J38*$C$38)+(J39*$C$39)+(J40*$C$40)+(J41*$C$41)+(J42*$C$42) | K45: =(K13*$C$13)+(K15*$C$15)+(K16*$C$16)+(K17*$C$17)+(K18*$C$18)+(K19*$C$19)+(K20*$C$20)+(K22*$C$22)+(K23*$C$23)+(K24*$C$24)+(K25*$C$25)+(K27*$C$27)+(K28*$C$28)+(K29*$C$29)+(K31*$C$31)+(K32*$C$32)+(K33*$C$33)+(K35*$C$35)+(K36*$C$36)+(K37*$C$37)+(K38*$C$38)+(K39*$C$39)+(K40*$C$40)+(K41*$C$41)+(K42*$C$42)
A47: FSE - Custos Variáveis | F47: =(F13*$D$13)+(F15*$D$15)+(F16*$D$16)+(F17*$D$17)+(F18*$D$18)+(F19*$D$19)+(F20*$D$20)+(F22*$D$22)+(F23*$D$23)+(F24*$D$24)+(F25*$D$25)+(F27*$D$27)+(F28*$D$28)+(F29*$D$29)+(F31*$D$31)+(F32*$D$32)+(F33*$D$33)+(F35*$D$35)+(F36*$D$36)+(F37*$D$37)+(F38*$D$38)+(F39*$D$39)+(F40*$D$40)+(F41*$D$41)+(F42*$D$42) | G47: =(G13*$D$13)+(G15*$D$15)+(G16*$D$16)+(G17*$D$17)+(G18*$D$18)+(G19*$D$19)+(G20*$D$20)+(G22*$D$22)+(G23*$D$23)+(G24*$D$24)+(G25*$D$25)+(G27*$D$27)+(G28*$D$28)+(G29*$D$29)+(G31*$D$31)+(G32*$D$32)+(G33*$D$33)+(G35*$D$35)+(G36*$D$36)+(G37*$D$37)+(G38*$D$38)+(G39*$D$39)+(G40*$D$40)+(G41*$D$41)+(G42*$D$42) | H47: =(H13*$D$13)+(H15*$D$15)+(H16*$D$16)+(H17*$D$17)+(H18*$D$18)+(H19*$D$19)+(H20*$D$20)+(H22*$D$22)+(H23*$D$23)+(H24*$D$24)+(H25*$D$25)+(H27*$D$27)+(H28*$D$28)+(H29*$D$29)+(H31*$D$31)+(H32*$D$32)+(H33*$D$33)+(H35*$D$35)+(H36*$D$36)+(H37*$D$37)+(H38*$D$38)+(H39*$D$39)+(H40*$D$40)+(H41*$D$41)+(H42*$D$42) | I47: =(I13*$D$13)+(I15*$D$15)+(I16*$D$16)+(I17*$D$17)+(I18*$D$18)+(I19*$D$19)+(I20*$D$20)+(I22*$D$22)+(I23*$D$23)+(I24*$D$24)+(I25*$D$25)+(I27*$D$27)+(I28*$D$28)+(I29*$D$29)+(I31*$D$31)+(I32*$D$32)+(I33*$D$33)+(I35*$D$35)+(I36*$D$36)+(I37*$D$37)+(I38*$D$38)+(I39*$D$39)+(I40*$D$40)+(I41*$D$41)+(I42*$D$42) | J47: =(J13*$D$13)+(J15*$D$15)+(J16*$D$16)+(J17*$D$17)+(J18*$D$18)+(J19*$D$19)+(J20*$D$20)+(J22*$D$22)+(J23*$D$23)+(J24*$D$24)+(J25*$D$25)+(J27*$D$27)+(J28*$D$28)+(J29*$D$29)+(J31*$D$31)+(J32*$D$32)+(J33*$D$33)+(J35*$D$35)+(J36*$D$36)+(J37*$D$37)+(J38*$D$38)+(J39*$D$39)+(J40*$D$40)+(J41*$D$41)+(J42*$D$42) | K47: =(K13*$D$13)+(K15*$D$15)+(K16*$D$16)+(K17*$D$17)+(K18*$D$18)+(K19*$D$19)+(K20*$D$20)+(K22*$D$22)+(K23*$D$23)+(K24*$D$24)+(K25*$D$25)+(K27*$D$27)+(K28*$D$28)+(K29*$D$29)+(K31*$D$31)+(K32*$D$32)+(K33*$D$33)+(K35*$D$35)+(K36*$D$36)+(K37*$D$37)+(K38*$D$38)+(K39*$D$39)+(K40*$D$40)+(K41*$D$41)+(K42*$D$42)
A49: TOTAL FSE | F49: =F45+F47 | G49: =G45+G47 | H49: =H45+H47 | I49: =I45+I47 | J49: =J45+J47 | K49: =K45+K47
A51: IVA | F51: =(F13*$B$13)+(F15*$B$15)+(F16*$B$16)+(F17*$B$17)+(F18*$B$18)+(F19*$B$19)+(F20*$B$20)+(F22*$B$22)+(F23*$B$23)+(F24*$B$24)+(F25*$B$25)+(F27*$B$27)+(F29*$B$29)+(F36*$B$36)+(F41*$B$41) | G51: =(G13*$B$13)+(G15*$B$15)+(G16*$B$16)+(G17*$B$17)+(G18*$B$18)+(G19*$B$19)+(G20*$B$20)+(G22*$B$22)+(G23*$B$23)+(G24*$B$24)+(G25*$B$25)+(G27*$B$27)+(G29*$B$29)+(G36*$B$36)+(G41*$B$41) | H51: =(H13*$B$13)+(H15*$B$15)+(H16*$B$16)+(H17*$B$17)+(H18*$B$18)+(H19*$B$19)+(H20*$B$20)+(H22*$B$22)+(H23*$B$23)+(H24*$B$24)+(H25*$B$25)+(H27*$B$27)+(H29*$B$29)+(H36*$B$36)+(H41*$B$41) | I51: =(I13*$B$13)+(I15*$B$15)+(I16*$B$16)+(I17*$B$17)+(I18*$B$18)+(I19*$B$19)+(I20*$B$20)+(I22*$B$22)+(I23*$B$23)+(I24*$B$24)+(I25*$B$25)+(I27*$B$27)+(I29*$B$29)+(I36*$B$36)+(I41*$B$41) | J51: =(J13*$B$13)+(J15*$B$15)+(J16*$B$16)+(J17*$B$17)+(J18*$B$18)+(J19*$B$19)+(J20*$B$20)+(J22*$B$22)+(J23*$B$23)+(J24*$B$24)+(J25*$B$25)+(J27*$B$27)+(J29*$B$29)+(J36*$B$36)+(J41*$B$41) | K51: =(K13*$B$13)+(K15*$B$15)+(K16*$B$16)+(K17*$B$17)+(K18*$B$18)+(K19*$B$19)+(K20*$B$20)+(K22*$B$22)+(K23*$B$23)+(K24*$B$24)+(K25*$B$25)+(K27*$B$27)+(K29*$B$29)+(K36*$B$36)+(K41*$B$41)
A53: FSE + IVA | F53: =F43+F51 | G53: =G43+G51 | H53: =H43+H51 | I53: =I43+I51 | J53: =J43+J51 | K53: =K43+K51

Sheet Gastos com Pessoal
H1: =+VN!G1 | I1: =+Pressupostos!E1
I2: =+Pressupostos!B9
A4: Gastos com o Pessoal
D6: =+VN!C8 | E6: =+VN!D8 | F6: =+VN!E8 | G6: =+VN!F8 | H6: =+VN!G8 | I6: =+VN!H8
A7: N.º Meses (pagos em ano normal) | D7: 14 | E7: 14 | F7: 14 | G7: 14 | H7: =+G7 | I7: =+H7
A8: Incremento Anual (Vencimentos + Sub. Almoço) % | D8: 0
A9: Meses de atividade da empresa (incluindo paragem em férias) | D9: 12 | E9: 12 | F9: 12 | G9: 12 | H9: 12 | I9: 12
A11: Quadro de Pessoal (N.º Pessoas) | D11: =+D6 | E11: =+E6 | F11: =+F6 | G11: =+G6 | H11: =+H6 | I11: =+I6
A12: Administração / Direção
A13: Administrativa / Financeira
A14: Comercial / Marketing
A15: Produção / Operacional
A16: Qualidade
A17: Manutenção
A18: Aprovisionamento
A19: Investigação e Desenvolvimento
A20: Outros
A23: TOTAL | D23: =+SUM(D12:D22) | E23: =+SUM(E12:E22) | F23: =+SUM(F12:F22) | G23: =+SUM(G12:G22) | H23: =+SUM(H12:H22) | I23: =+SUM(I12:I22)
A26: Quadro de Pessoal (Meses de Trabalho incluindo Tempo Férias) | D26: =+D21 | E26: =+E21 | F26: =+F21 | G26: =+G21 | H26: =+H21 | I26: =+I21
A27: =+A12
A28: =+A13
A29: =+A14
A30: =+A15
A31: =+A16
A32: =+A17
A33: =+A18
A34: =+A19
A35: =+A20
A36: =+A21
A37: =+A22
A40: Remuneração Base Mensal | D40: =+D11 | E40: =+E11 | F40: =+F11 | G40: =+G11 | H40: =+H11 | I40: =+I11
A41: =+A12
A42: =+A13
A43: =+A14
A44: =+A15
A45: =+A16
A46: =+A17
A47: =+A18
A48: =+A19
A49: =+A20
A50: =+A21
A51: =+A22
A54: Remuneração Base Anual - TOTAL Colaboradores | D54: =+D40 | E54: =+E40 | F54: =+F40 | G54: =+G40 | H54: =+H40 | I54: =+I40
A55: =+A41 | D55: =+D12*D27/12*D41*$D$7 | E55: =+E12*E27/12*E41*$E$7 | F55: =+F12*F27/12*F41*$F$7 | G55: =+G12*G27/12*G41*$G$7 | H55: =+H12*H27/12*H41*$H$7 | I55: =+I12*I27/12*I41*$I$7
A56: =+A42 | D56: =+D13*D28/12*D42*$D$7 | E56: =+E13*E28/12*E42*$E$7 | F56: =+F13*F28/12*F42*$F$7 | G56: =+G13*G28/12*G42*$G$7 | H56: =+H13*H28/12*H42*$H$7 | I56: =+I13*I28/12*I42*$I$7
A57: =+A43 | D57: =+D14*D29/12*D43*$D$7 | E57: =+E14*E29/12*E43*$E$7 | F57: =+F14*F29/12*F43*$F$7 | G57: =+G14*G29/12*G43*$G$7 | H57: =+H14*H29/12*H43*$H$7 | I57: =+I14*I29/12*I43*$I$7
A58: =+A44 | D58: =+D15*D30/12*D44*$D$7 | E58: =+E15*E30/12*E44*$E$7 | F58: =+F15*F30/12*F44*$F$7 | G58: =+G15*G30/12*G44*$G$7 | H58: =+H15*H30/12*H44*$H$7 | I58: =+I15*I30/12*I44*$I$7
A59: =+A45 | D59: =+D16*D31/12*D45*$D$7 | E59: =+E16*E31/12*E45*$E$7 | F59: =+F16*F31/12*F45*$F$7 | G59: =+G16*G31/12*G45*$G$7 | H59: =+H16*H31/12*H45*$H$7 | I59: =+I16*I31/12*I45*$I$7
A60: =+A46 | D60: =+D17*D32/12*D46*$D$7 | E60: =+E17*E32/12*E46*$E$7 | F60: =+F17*F32/12*F46*$F$7 | G60: =+G17*G32/12*G46*$G$7 | H60: =+H17*H32/12*H46*$H$7 | I60: =+I17*I32/12*I46*$I$7
A61: =+A47 | D61: =+D18*D33/12*D47*$D$7 | E61: =+E18*E33/12*E47*$E$7 | F61: =+F18*F33/12*F47*$F$7 | G61: =+G18*G33/12*G47*$G$7 | H61: =+H18*H33/12*H47*$H$7 | I61: =+I18*I33/12*I47*$I$7
A62: =+A48 | D62: =+D19*D34/12*D48*$D$7 | E62: =+E19*E34/12*E48*$E$7 | F62: =+F19*F34/12*F48*$F$7 | G62: =+G19*G34/12*G48*$G$7 | H62: =+H19*H34/12*H48*$H$7 | I62: =+I19*I34/12*I48*$I$7
A63: =+A49 | D63: =+D20*D35/12*D49*$D$7 | E63: =+E20*E35/12*E49*$E$7 | F63: =+F20*F35/12*F49*$F$7 | G63: =+G20*G35/12*G49*$G$7 | H63: =+H20*H35/12*H49*$H$7 | I63: =+I20*I35/12*I49*$I$7
A64: =+A50 | D64: =+D21*D36/12*D50*$D$7 | E64: =+E21*E36/12*E50*$E$7 | F64: =+F21*F36/12*F50*$F$7 | G64: =+G21*G36/12*G50*$G$7 | H64: =+H21*H36/12*H50*$H$7 | I64: =+I21*I36/12*I50*$I$7
A65: =+A51 | D65: =+D22*D37/12*D51*$D$7 | E65: =+E22*E37/12*E51*$E$7 | F65: =+F22*F37/12*F51*$F$7 | G65: =+G22*G37/12*G51*$G$7 | H65: =+H22*H37/12*H51*$H$7 | I65: =+I22*I37/12*I51*$I$7
A66: TOTAL | D66: =+SUM(D55:D65) | E66: =+SUM(E55:E65) | F66: =+SUM(F55:F65) | G66: =+SUM(G55:G65) | H66: =+SUM(H55:H65) | I66: =+SUM(I55:I65)
A69: Outros Gastos | D69: =+D6 | E69: =+E6 | F69: =+F6 | G69: =+G6 | H69: =+H6 | I69: =+I6
A70: Segurança Social
A71: Órgãos Sociais | C71: =+Pressupostos!B24 | D71: =$C$71*(D55+D77) | E71: =$C$71*(E55+E77) | F71: =$C$71*(F55+F77) | G71: =$C$71*(G55+G77) | H71: =$C$71*(H55+H77) | I71: =$C$71*(I55+I77)
A72: Pessoal | C72: =+Pressupostos!B25 | D72: =+$C$72*(SUM(D56:D65)+D78) | E72: =+$C$72*(SUM(E56:E65)+E78) | F72: =+$C$72*(SUM(F56:F65)+F78) | G72: =+$C$72*(SUM(G56:G65)+G78) | H72: =+$C$72*(SUM(H56:H65)+H78) | I72: =+$C$72*(SUM(I56:I65)+I78)
A73: Seguros Acidentes de Trabalho | C73: 0.01 | D73: =+$C$73*D66 | E73: =+$C$73*E66 | F73: =+$C$73*F66 | G73: =+$C$73*G66 | H73: =+$C$73*H66 | I73: =+$C$73*I66
A74: Subsídio Alimentação - N.º Dias Úteis/Mês x Subsídio/Dia | C74: =4.77*22 | D74: =+$C$74*D75*D23 | E74: =+$C$74*E75*E23 | F74: =+$C$74*F75*F23 | G74: =+$C$74*G75*G23 | H74: =+$C$74*H75*H23 | I74: =+$C$74*I75*I23
A75: N.º Meses Subsídio Alimentação (Meses) | D75: =IF(D9<12,D9/12*11,11) | E75: =IF(E9<12,E9/12*11,11) | F75: =IF(F9<12,F9/12*11,11) | G75: =IF(G9<12,G9/12*11,11) | H75: =IF(H9<12,H9/12*11,11) | I75: =IF(I9<12,I9/12*11,11)
A76: Comissões & Prémios
A77: Órgãos Sociais
A78: Pessoal
A79: Formação
A80: Outros Custos com Pessoal
A81: TOTAL OUTROS GASTOS | D81: =+D71+D72+D73+D74+D77+D78+D79+D80 | E81: =+E71+E72+E73+E74+E77+E78+E79+E80 | F81: =+F71+F72+F73+F74+F77+F78+F79+F80 | G81: =+G71+G72+G73+G74+G77+G78+G79+G80 | H81: =+H71+H72+H73+H74+H77+H78+H79+H80 | I81: =+I71+I72+I73+I74+I77+I78+I79+I80
A83: TOTAL GASTOS COM PESSOAL | D83: =D66+D81 | E83: =E66+E81 | F83: =F66+F81 | G83: =G66+G81 | H83: =H66+H81 | I83: =I66+I81
A86: QUADRO RESUMO | D86: =+D6 | E86: =+E6 | F86: =+F6 | G86: =+G6 | H86: =+H6 | I86: =+I6
A87: Remunerações
A88: Órgãos Sociais | D88: =D55+D77 | E88: =E55+E77 | F88: =F55+F77 | G88: =G55+G77 | H88: =H55+H77 | I88: =I55+I77
A89: Pessoal | D89: =+SUM(D56:D65)+D78 | E89: =+SUM(E56:E65)+E78 | F89: =+SUM(F56:F65)+F78 | G89: =+SUM(G56:G65)+G78 | H89: =+SUM(H56:H65)+H78 | I89: =+SUM(I56:I65)+I78
A90: Encargos sobre Remunerações | D90: =+D71+D72 | E90: =+E71+E72 | F90: =+F71+F72 | G90: =+G71+G72 | H90: =+H71+H72 | I90: =+I71+I72
A91: Seguros Acidentes de Trabalho e Doenças Profissionais | D91: =+D73 | E91: =+E73 | F91: =+F73 | G91: =+G73 | H91: =+H73 | I91: =+I73
A92: Gastos de Ação Social | D92: =+D74 | E92: =+E74 | F92: =+F74 | G92: =+G74 | H92: =+H74 | I92: =+I74
A93: Outros Gastos com Pessoal | D93: =+D79+D80 | E93: =+E79+E80 | F93: =+F79+F80 | G93: =+G79+G80 | H93: =+H79+H80 | I93: =+I79+I80
A94: TOTAL GASTOS COM PESSOAL | D94: =SUM(D88:D93) | E94: =SUM(E88:E93) | F94: =SUM(F88:F93) | G94: =SUM(G88:G93) | H94: =SUM(H88:H93) | I94: =SUM(I88:I93)
A97: Retenções Colaboradores | D97: =+D86 | E97: =+E86 | F97: =+F86 | G97: =+G86 | H97: =+H86 | I97: =+I86
A98: Retenção SS Colaborador
A99: Gerência / Administração | C99: =+Pressupostos!B26 | D99: =+$C$99*D88 | E99: =+$C$99*E88 | F99: =+$C$99*F88 | G99: =+$C$99*G88 | H99: =+$C$99*H88 | I99: =+$C$99*I88
A100: Outro Pessoal | C100: =+Pressupostos!B27 | D100: =+$C$100*D89 | E100: =+$C$100*E89 | F100: =+$C$100*F89 | G100: =+$C$100*G89 | H100: =+$C$100*H89 | I100: =+$C$100*I89
A101: Retenção IRS Colaborador | C101: =+Pressupostos!B28 | D101: =+$C$101*(D88+D89) | E101: =+$C$101*(E88+E89) | F101: =+$C$101*(F88+F89) | G101: =+$C$101*(G88+G89) | H101: =+$C$101*(H88+H89) | I101: =+$C$101*(I88+I89)
A102: TOTAL Retenções | D102: =SUM(D99:D101) | E102: =SUM(E99:E101) | F102: =SUM(F99:F101) | G102: =SUM(G99:G101) | H102: =SUM(H99:H101) | I102: =SUM(I99:I101)

Sheet FundoManeio
G1: Empresa: | H1: =+Pressupostos!E1
H2: =+Pressupostos!B9
A4: Investimento em Fundo Maneio Necessário
C7: =+VN!C8 | D7: =+VN!D8 | E7: =+VN!E8 | F7: =+VN!F8 | G7: =+VN!G8 | H7: =+VN!H8
A8: Necessidades Fundo Maneio
A9: Reserva Segurança Tesouraria (valor fixo) | D9: =+C9 | E9: =+D9 | F9: =+E9 | G9: =+F9 | H9: =+G9
A10: Clientes | C10: =VN!C84*Pressupostos!$C$13/12 | D10: =VN!D84*Pressupostos!$C$13/12 | E10: =VN!E84*Pressupostos!$C$13/12 | F10: =VN!F84*Pressupostos!$C$13/12 | G10: =VN!G84*Pressupostos!$C$13/12 | H10: =VN!H84*Pressupostos!$C$13/12
A11: Inventários | C11: =CMVMC!C16*Pressupostos!$C$15/12 | D11: =CMVMC!D16*Pressupostos!$C$15/12 | E11: =CMVMC!E16*Pressupostos!$C$15/12 | F11: =CMVMC!F16*Pressupostos!$C$15/12 | G11: =CMVMC!G16*Pressupostos!$C$15/12 | H11: =CMVMC!H16*Pressupostos!$C$15/12
A12: Estado | C12: =IF(C30<0,-C30,0)+IF(C31<0,-C31,0)+IF(C32<0,-C32,0) | D12: =IF(D30<0,-D30,0)+IF(D31<0,-D31,0)+IF(D32<0,-D32,0) | E12: =IF(E30<0,-E30,0)+IF(E31<0,-E31,0)+IF(E32<0,-E32,0) | F12: =IF(F30<0,-F30,0)+IF(F31<0,-F31,0)+IF(F32<0,-F32,0) | G12: =IF(G30<0,-G30,0)+IF(G31<0,-G31,0)+IF(G32<0,-G32,0) | H12: =IF(H30<0,-H30,0)+IF(H31<0,-H31,0)+IF(H32<0,-H32,0)
A13: *
A14: *
A15: TOTAL | C15: =SUM(C9:C14) | D15: =SUM(D9:D14) | E15: =SUM(E9:E14) | F15: =SUM(F9:F14) | G15: =SUM(G9:G14) | H15: =SUM(H9:H14)
A16: Recursos Fundo Maneio
A17: Fornecedores | C17: =(CMVMC!C20+FSE!F53)*Pressupostos!$C$14/12 | D17: =(CMVMC!D20+FSE!G53)*Pressupostos!$C$14/12 | E17: =(CMVMC!E20+FSE!H53)*Pressupostos!$C$14/12 | F17: =(CMVMC!F20+FSE!I53)*Pressupostos!$C$14/12 | G17: =(CMVMC!G20+FSE!J53)*Pressupostos!$C$14/12 | H17: =(CMVMC!H20+FSE!K53)*Pressupostos!$C$14/12
A18: Estado | C18: =IF(C30>0,C30,0)+IF(C31>0,C31,0)+IF(C32>0,C32,0) | D18: =IF(D30>0,D30,0)+IF(D31>0,D31,0)+IF(D32>0,D32,0) | E18: =IF(E30>0,E30,0)+IF(E31>0,E31,0)+IF(E32>0,E32,0) | F18: =IF(F30>0,F30,0)+IF(F31>0,F31,0)+IF(F32>0,F32,0) | G18: =IF(G30>0,G30,0)+IF(G31>0,G31,0)+IF(G32>0,G32,0) | H18: =IF(H30>0,H30,0)+IF(H31>0,H31,0)+IF(H32>0,H32,0)
A19: *
A20: TOTAL | C20: =+SUM(C17:C19) | D20: =+SUM(D17:D19) | E20: =+SUM(E17:E19) | F20: =+SUM(F17:F19) | G20: =+SUM(G17:G19) | H20: =+SUM(H17:H19)
A22: Fundo Maneio Necessário | C22: =+C15-C20 | D22: =+D15-D20 | E22: =+E15-E20 | F22: =+F15-F20 | G22: =+G15-G20 | H22: =+H15-H20
A24: Investimento em Fundo de Maneio | C24: =+C22 | D24: =+D22-C22 | E24: =+E22-D22 | F24: =+F22-E22 | G24: =+G22-F22 | H24: =+H22-G22
A26: * A considerar caso seja necessário
A29: ESTADO | C29: =+SUM(C30:C32) | D29: =+SUM(D30:D32) | E29: =+SUM(E30:E32) | F29: =+SUM(F30:F32) | G29: =+SUM(G30:G32) | H29: =+SUM(H30:H32)
A30: SS | C30: =IF('Gastos com Pessoal'!D$7=0, 0,('Gastos com Pessoal'!D99+'Gastos com Pessoal'!D100+'Gastos com Pessoal'!D71+'Gastos com Pessoal'!D72)/'Gastos com Pessoal'!D$7) | D30: =IF('Gastos com Pessoal'!E$7=0,0,('Gastos com Pessoal'!E99+'Gastos com Pessoal'!E100+'Gastos com Pessoal'!E71+'Gastos com Pessoal'!E72)/'Gastos com Pessoal'!E$7) | E30: =('Gastos com Pessoal'!F99+'Gastos com Pessoal'!F100+'Gastos com Pessoal'!F71+'Gastos com Pessoal'!F72)/'Gastos com Pessoal'!F$7 | F30: =('Gastos com Pessoal'!G99+'Gastos com Pessoal'!G100+'Gastos com Pessoal'!G71+'Gastos com Pessoal'!G72)/'Gastos com Pessoal'!G$7 | G30: =('Gastos com Pessoal'!H99+'Gastos com Pessoal'!H100+'Gastos com Pessoal'!H71+'Gastos com Pessoal'!H72)/'Gastos com Pessoal'!H$7 | H30: =('Gastos com Pessoal'!I99+'Gastos com Pessoal'!I100+'Gastos com Pessoal'!I71+'Gastos com Pessoal'!I72)/'Gastos com Pessoal'!I$7
A31: IRS | C31: =IF('Gastos com Pessoal'!D7=0,0,'Gastos com Pessoal'!D101/'Gastos com Pessoal'!D7) | D31: =IF('Gastos com Pessoal'!E7=0,0,'Gastos com Pessoal'!E101/'Gastos com Pessoal'!E7) | E31: ='Gastos com Pessoal'!F101/'Gastos com Pessoal'!F7 | F31: ='Gastos com Pessoal'!G101/'Gastos com Pessoal'!G7 | G31: ='Gastos com Pessoal'!H101/'Gastos com Pessoal'!H7 | H31: ='Gastos com Pessoal'!I101/'Gastos com Pessoal'!I7
A32: IVA | C32: =(VN!C82-CMVMC!C18-FSE!F51-Investimento!C33)/Pressupostos!$C$16 | D32: =(VN!D82-CMVMC!D18-FSE!G51-Investimento!D33)/Pressupostos!$C$16 | E32: =(VN!E82-CMVMC!E18-FSE!H51-Investimento!E33)/Pressupostos!$C$16 | F32: =(VN!F82-CMVMC!F18-FSE!I51-Investimento!F33)/Pressupostos!$C$16 | G32: =(VN!G82-CMVMC!G18-FSE!J51-Investimento!G33)/Pressupostos!$C$16 | H32: =(VN!H82-CMVMC!H18-FSE!K51-Investimento!H33)/Pressupostos!$C$16

Sheet Investimento
G1: Empresa: | H1: =+Pressupostos!E1
H2: =+Pressupostos!B9
A4: Investimento
A7: Investimento por Ano | C7: =+VN!C8 | D7: =+VN!D8 | E7: =+VN!E8 | F7: =+VN!F8 | G7: =+VN!G8 | H7: =+VN!H8
A8: Propriedades de Investimento
A9: Terrenos e Recursos Naturais
A10: Edifícios e Outras Construções
A11: Outras Propriedades de Investimento
A12: Total Propriedades de Investimento | C12: =+SUM(C9:C11) | D12: =+SUM(D9:D11) | E12: =+SUM(E9:E11) | F12: =+SUM(F9:F11) | G12: =+SUM(G9:G11) | H12: =+SUM(H9:H11)
A13: Ativos Fixos Tangíveis
A14: Terrenos e Recursos Naturais
A15: Edifícios e Outras Construções
A16: Equipamento Básico
A17: Equipamento de Transporte
A18: Equipamento Administrativo
A19: Equipamentos Biológicos
A20: Outros Ativos Fixos Tangíveis
A21: Total Ativos Fixos Tangíveis | C21: =+SUM(C14:C20) | D21: =+SUM(D14:D20) | E21: =+SUM(E14:E20) | F21: =+SUM(F14:F20) | G21: =+SUM(G14:G20) | H21: =+SUM(H14:H20)
A22: Ativos Intangíveis
A23: Goodwill
A24: Projetos de Desenvolvimento
A25: Programas de Computador
A26: Propriedade Industrial
A27: Outros Ativos Intangíveis
A28: Total Ativos Intangíveis | C28: =+SUM(C23:C27) | D28: =+SUM(D23:D27) | E28: =+SUM(E23:E27) | F28: =+SUM(F23:F27) | G28: =+SUM(G23:G27) | H28: =+SUM(H23:H27)
A29: Total Investimento | C29: =+C12+C21+C28 | D29: =+D12+D21+D28 | E29: =+E12+E21+E28 | F29: =+F12+F21+F28 | G29: =+G12+G21+G28 | H29: =+H12+H21+H28
A31: N.º Meses Atividade/Produção | C31: =+'Gastos com Pessoal'!D9 | D31: =+'Gastos com Pessoal'!E9 | E31: =+'Gastos com Pessoal'!F9 | F31: =+'Gastos com Pessoal'!G9 | G31: =+'Gastos com Pessoal'!H9 | H31: =+'Gastos com Pessoal'!I9
A33: IVA | B33: =+Pressupostos!B22 | C33: =+$B$33*(C16+C18+C20+C25) | D33: =+$B$33*(D16+D18+D20+D25) | E33: =+$B$33*(E16+E18+E20+E25) | F33: =+$B$33*(F16+F18+F20+F25) | G33: =+$B$33*(G16+G18+G20+G25) | H33: =+$B$33*(H16+H18+H20+H25)
A35: Valores Acumulados | C35: =+C7 | D35: =+D7 | E35: =+E7 | F35: =+F7 | G35: =+G7 | H35: =+H7
A36: Propriedades de Investimento
A37: Terrenos e Recursos Naturais | C37: =+C9 | D37: =+C37+D9 | E37: =+D37+E9 | F37: =+E37+F9 | G37: =+F37+G9 | H37: =+G37+H9
A38: Edifícios e Outras Construções | C38: =+C10 | D38: =+C38+D10 | E38: =+D38+E10 | F38: =+E38+F10 | G38: =+F38+G10 | H38: =+G38+H10
A39: Outras Propriedades de Investimento | C39: =+C11 | D39: =+C39+D11 | E39: =+D39+E11 | F39: =+E39+F11 | G39: =+F39+G11 | H39: =+G39+H11
A40: Total Propriedades de Investimento | C40: =+SUM(C37:C39) | D40: =+SUM(D37:D39) | E40: =+SUM(E37:E39) | F40: =+SUM(F37:F39) | G40: =+SUM(G37:G39) | H40: =+SUM(H37:H39)
A41: Ativos Fixos Tangíveis
A42: Terrenos e Recursos Naturais | C42: =+C14 | D42: =+C42+D14 | E42: =+D42+E14 | F42: =+E42+F14 | G42: =+F42+G14 | H42: =+G42+H14
A43: Edifícios e Outras Construções | C43: =+C15 | D43: =+C43+D15 | E43: =+D43+E15 | F43: =+E43+F15 | G43: =+F43+G15 | H43: =+G43+H15
A44: Equipamento Básico | C44: =+C16 | D44: =+C44+D16 | E44: =+D44+E16 | F44: =+E44+F16 | G44: =+F44+G16 | H44: =+G44+H16
A45: Equipamento de Transporte | C45: =+C17 | D45: =+C45+D17 | E45: =+D45+E17 | F45: =+E45+F17 | G45: =+F45+G17 | H45: =+G45+H17
A46: Equipamento Administrativo | C46: =+C18 | D46: =+C46+D18 | E46: =+D46+E18 | F46: =+E46+F18 | G46: =+F46+G18 | H46: =+G46+H18
A47: Equipamentos Biológicos | C47: =+C19 | D47: =+C47+D19 | E47: =+D47+E19 | F47: =+E47+F19 | G47: =+F47+G19 | H47: =+G47+H19
A48: Outros Ativos Fixos Tangíveis | C48: =+C20 | D48: =+C48+D20 | E48: =+D48+E20 | F48: =+E48+F20 | G48: =+F48+G20 | H48: =+G48+H20
A49: Total Ativos Fixos Tangíveis | C49: =+SUM(C42:C48) | D49: =+SUM(D42:D48) | E49: =+SUM(E42:E48) | F49: =+SUM(F42:F48) | G49: =+SUM(G42:G48) | H49: =+SUM(H42:H48)
A50: Ativos Intangíveis
A51: Goodwill | C51: =+C23 | D51: =+C51+D23 | E51: =+D51+E23 | F51: =+E51+F23 | G51: =+F51+G23 | H51: =+G51+H23
A52: Projetos de Desenvolvimento | C52: =+C24 | D52: =+C52+D24 | E52: =+D52+E24 | F52: =+E52+F24 | G52: =+F52+G24 | H52: =+G52+H24
A53: Programas de Computador | C53: =+C25 | D53: =+C53+D25 | E53: =+D53+E25 | F53: =+E53+F25 | G53: =+F53+G25 | H53: =+G53+H25
A54: Propriedade Industrial | C54: =+C26 | D54: =+C54+D26 | E54: =+D54+E26 | F54: =+E54+F26 | G54: =+F54+G26 | H54: =+G54+H26
A55: Outros Ativos Intangíveis | C55: =+C27 | D55: =+C55+D27 | E55: =+D55+E27 | F55: =+E55+F27 | G55: =+F55+G27 | H55: =+G55+H27
A56: Total Ativos Intangíveis | C56: =+SUM(C51:C55) | D56: =+SUM(D51:D55) | E56: =+SUM(E51:E55) | F56: =+SUM(F51:F55) | G56: =+SUM(G51:G55) | H56: =+SUM(H51:H55)
A57: Total | C57: =+C40+C49+C56 | D57: =+D40+D49+D56 | E57: =+E40+E49+E56 | F57: =+F40+F49+F56 | G57: =+G40+G49+G56 | H57: =+H40+H49+H56
A60: Taxas de Depreciações e Amortizações | D60: Utilizar tabela "legal" de amortizações e se necessário calcular Taxa médias por tipo de investimento
A61: Propriedades de Investimento
A62: Edifícios e Outras Construções | C62: 0.04
A63: Outras Propriedades de Investimento | C63: 0.2
A64: Ativos Fixos Tangíveis
A65: Edifícios e Outras Construções | C65: 0.05
A66: Equipamento Básico | C66: 0.125
A67: Equipamento de Transporte | C67: 0.25
A68: Equipamento Administrativo | C68: 0.25
A69: Equipamentos Biológicos | C69: 0.2
A70: Outros Ativos Fixos Tangíveis | C70: 0.25
A71: Ativos Intangíveis
A72: Projetos de Desenvolvimento | C72: =0.333333333333333*100% | D72: * Nota: se a taxa a utilizar for 33,33%, colocar mais uma casa decimal, considerando 33,333%
A73: Programas de Computador | C73: =0.333333333333333*100%
A74: Propriedade Industrial | C74: =0.333333333333333*100%
A75: Outros Ativos Intangíveis | C75: =0.333333333333333*100%
A77: Depreciações e amortizações | C77: =+C7 | D77: =+C77+1 | E77: =+D77+1 | F77: =+E77+1 | G77: =+F77+1 | H77: =+G77+1
A78: Propriedades de investimento
A79: Edificios e Outras construções | B79: =+C62 | C79: =SUM(C80:C85) | D79: =SUM(D80:D85) | E79: =SUM(E80:E85) | F79: =SUM(F80:F85) | G79: =SUM(G80:G85) | H79: =SUM(H80:H85)
A80: =C77 | C80: =+IF(C$10<0,0,C$10*$B$79)/12*C$31 | D80: =+IF(AND(C80>0,C10>0),+IF(ROUNDUP(SUM($C80:C80),0)<C10,+C10*$B79*(C$31/12)),C10*$B79*(D$31/12)) | E80: =+IF(D80=0,0,+IF(ROUNDUP(SUM($C80:D80),0)<$C$10,MIN(($C$10-SUM($C80:D80)),$C$10*$B$79),0)) | F80: =+IF(E80=0,0,+IF(ROUNDUP(SUM($C80:E80),0)<$C$10,MIN(($C$10-SUM($C80:E80)),$C$10*$B$79),0)) | G80: =+IF(F80=0,0,+IF(ROUNDUP(SUM($C80:F80),0)<$C$10,MIN(($C$10-SUM($C80:F80)),$C$10*$B$79),0)) | H80: =+IF(G80=0,0,+IF(ROUNDUP(SUM($C80:G80),0)<$C$10,MIN(($C$10-SUM($C80:G80)),$C$10*$B$79),0))
A81: =A80+1 | D81: =+IF(D$10<0,0,D$10*$B$79)/12*D$31 | E81: =+IF(D81=0,0,+IF(ROUNDUP(SUM(D$81:$D81),0)<$D$10,MIN(($D$10-SUM($D81:D81)),$D$10*$B$79),0)) | F81: =+IF(E81=0,0,+IF(ROUNDUP(SUM($D$81:E81),0)<$D$10,MIN(($D$10-SUM($D81:E81)),$D$10*$B$79),0)) | G81: =+IF(F81=0,0,+IF(ROUNDUP(SUM($D$81:F81),0)<$D$10,MIN(($D$10-SUM($D81:F81)),$D$10*$B$79),0)) | H81: =+IF(G81=0,0,+IF(ROUNDUP(SUM($D$81:G81),0)<$D$10,MIN(($D$10-SUM($D81:G81)),$D$10*$B$79),0))
A82: =A81+1 | E82: =+IF(E$10<0,0,E$10*$B$79)/12*E$31 | F82: =+IF(E82=0,0,+IF(ROUNDUP(SUM($E$81:E82),0)<$E$10,MIN(($E$10-SUM($E82:E82)),$E$10*$B$79),0)) | G82: =+IF(F82=0,0,+IF(ROUNDUP(SUM($E$81:F82),0)<$E$10,MIN(($E$10-SUM($E82:F82)),$E$10*$B$79),0)) | H82: =+IF(G82=0,0,+IF(ROUNDUP(SUM($E$81:G82),0)<$E$10,MIN(($E$10-SUM($E82:G82)),$E$10*$B$79),0))
A83: =A82+1 | F83: =+IF(F$10<0,0,F$10*$B$79)/12*F$31 | G83: =+IF(F83=0,0,+IF(ROUNDUP(SUM($F$81:F83),0)<$F$10,MIN(($F$10-SUM($F83:F83)),$F$10*$B$79),0)) | H83: =+IF(G83=0,0,+IF(ROUNDUP(SUM($F$81:G83),0)<$F$10,MIN(($F$10-SUM($F83:G83)),$F$10*$B$79),0))
A84: =A83+1 | G84: =+IF(G$10<0,0,G$10*$B$79)/12*G$31 | H84: =+IF(G84=0,0,+IF(ROUNDUP(SUM($G$81:G84),0)<$G$10,MIN(($G$10-SUM($G84:G84)),$G$10*$B$79),0))
A85: =A84+1 | H85: =+IF(H$10<0,0,H$10*$B$79)/12*H$31
A86: Outras propriedades de investimento | B86: =+C63 | C86: =SUM(C87:C92) | D86: =SUM(D87:D92) | E86: =SUM(E87:E92) | F86: =SUM(F87:F92) | G86: =SUM(G87:G92) | H86: =SUM(H87:H92)
A87: =A80 | C87: =+IF(C$11<0,0,C$11*$B$86)/12*$C$31 | D87: =+IF(AND(C87>0,C11>0),+IF(ROUNDUP(SUM($C87:C87),0)<C11,+C11*$B86*(C$31/12)),C11*$B86*(D$31/12)) | E87: =+IF(D87=0,0,+IF(ROUNDUP(SUM($C87:D87),0)<$C$11,MIN(($C$11-SUM($C87:D87)),$C$11*$B$86),0)) | F87: =+IF(E87=0,0,+IF(ROUNDUP(SUM($C87:E87),0)<$C$11,MIN(($C$11-SUM($C87:E87)),$C$11*$B$86),0)) | G87: =+IF(F87=0,0,+IF(ROUNDUP(SUM($C87:F87),0)<$C$11,MIN(($C$11-SUM($C87:F87)),$C$11*$B$86),0)) | H87: =+IF(G87=0,0,+IF(ROUNDUP(SUM($C87:G87),0)<$C$11,MIN(($C$11-SUM($C87:G87)),$C$11*$B$86),0))
A88: =A81 | D88: =+IF(D$11<0,0,D$11*$B$86)/12*$C$31 | E88: =+IF(D88=0,0,+IF(ROUNDUP(SUM($D88:D88),0)<$D$11,MIN(($D$11-SUM($D88:D88)),$D$11*$B$86),0)) | F88: =+IF(E88=0,0,+IF(ROUNDUP(SUM($D88:E88),0)<$D$11,MIN(($D$11-SUM($D88:E88)),$D$11*$B$86),0)) | G88: =+IF(F88=0,0,+IF(ROUNDUP(SUM($D88:F88),0)<$D$11,MIN(($D$11-SUM($D88:F88)),$D$11*$B$86),0)) | H88: =+IF(G88=0,0,+IF(ROUNDUP(SUM($D88:G88),0)<$D$11,MIN(($D$11-SUM($D88:G88)),$D$11*$B$86),0))
A89: =A82 | E89: =+IF(E$11<0,0,E$11*$B$86)/12*$C$31 | F89: =+IF(E89=0,0,+IF(ROUNDUP(SUM($E89:E89),0)<$E$11,MIN(($E$11-SUM($E89:E89)),$E$11*$B$86),0)) | G89: =+IF(F89=0,0,+IF(ROUNDUP(SUM($E89:F89),0)<$E$11,MIN(($E$11-SUM($E89:F89)),$E$11*$B$86),0)) | H89: =+IF(G89=0,0,+IF(ROUNDUP(SUM($E89:G89),0)<$E$11,MIN(($E$11-SUM($E89:G89)),$E$11*$B$86),0))
A90: =A83 | F90: =+IF(F$11<0,0,F$11*$B$86)/12*$C$31 | G90: =+IF(F90=0,0,+IF(ROUNDUP(SUM($F90:F90),0)<$F$11,MIN(($F$11-SUM($F90:F90)),$F$11*$B$86),0)) | H90: =+IF(G90=0,0,+IF(ROUNDUP(SUM($F90:G90),0)<$F$11,MIN(($F$11-SUM($F90:G90)),$F$11*$B$86),0))
A91: =A84 | G91: =+IF(G$11<0,0,G$11*$B$86)/12*$C$31 | H91: =+IF(G91=0,0,+IF(ROUNDUP(SUM($G91:G91),0)<$G$11,MIN(($G$11-SUM($G91:G91)),$G$11*$B$86),0))
A92: =A85 | H92: =+IF(H$11<0,0,H$11*$B$86)/12*$C$31
A93: TOTAL | C93: =+C79+C86 | D93: =+D79+D86 | E93: =+E79+E86 | F93: =+F79+F86 | G93: =+G79+G86 | H93: =+H79+H86
A94: Activos fixos tangíveis
A95: Edificios e Outras Construções | B95: =+C65 | C95: =SUM(C96:C101) | D95: =SUM(D96:D101) | E95: =SUM(E96:E101) | F95: =SUM(F96:F101) | G95: =SUM(G96:G101) | H95: =SUM(H96:H101)
A96: =A87 | C96: =+IF(C$15<0,0,C$15*$B$95)/12*C$31 | D96: =+IF(AND(C96>0,C15>0),+IF(ROUNDUP(SUM($C96:C96),0)<C15,+C15*$B95*(C$31/12)),C15*$B95*(D$31/12)) | E96: =+IF(D96=0,0,+IF(ROUNDUP(SUM($C96:D96),0)<$C$15,MIN(($C$15-SUM($C96:D96)),$C$15*$B$95),0)) | F96: =+IF(E96=0,0,+IF(ROUNDUP(SUM($C96:E96),0)<$C$15,MIN(($C$15-SUM($C96:E96)),$C$15*$B$95),0)) | G96: =+IF(F96=0,0,+IF(ROUNDUP(SUM($C96:F96),0)<$C$15,MIN(($C$15-SUM($C96:F96)),$C$15*$B$95),0)) | H96: =+IF(G96=0,0,+IF(ROUNDUP(SUM($C96:G96),0)<$C$15,MIN(($C$15-SUM($C96:G96)),$C$15*$B$95),0))
A97: =A88 | D97: =+IF(D$15<0,0,D$15*$B$95)/12*D$31 | E97: =+IF(D97=0,0,+IF(ROUNDUP(SUM($D97:D97),0)<$D$15,MIN(($D$15-SUM($D97:D97)),$D$15*$B$95),0)) | F97: =+IF(E97=0,0,+IF(ROUNDUP(SUM($D97:E97),0)<$D$15,MIN(($D$15-SUM($D97:E97)),$D$15*$B$95),0)) | G97: =+IF(F97=0,0,+IF(ROUNDUP(SUM($D97:F97),0)<$D$15,MIN(($D$15-SUM($D97:F97)),$D$15*$B$95),0)) | H97: =+IF(G97=0,0,+IF(ROUNDUP(SUM($D97:G97),0)<$D$15,MIN(($D$15-SUM($D97:G97)),$D$15*$B$95),0))
A98: =A89 | E98: =+IF(E$15<0,0,E$15*$B$95)/12*E$31 | F98: =+IF(E98=0,0,+IF(ROUNDUP(SUM($E98:E98),0)<$E$15,MIN(($E$15-SUM($E98:E98)),$E$15*$B$95),0)) | G98: =+IF(F98=0,0,+IF(ROUNDUP(SUM($E98:F98),0)<$E$15,MIN(($E$15-SUM($E98:F98)),$E$15*$B$95),0)) | H98: =+IF(G98=0,0,+IF(ROUNDUP(SUM($E98:G98),0)<$E$15,MIN(($E$15-SUM($E98:G98)),$E$15*$B$95),0))
A99: =A90 | F99: =+IF(F$15<0,0,F$15*$B$95)/12*F$31 | G99: =+IF(F99=0,0,+IF(ROUNDUP(SUM($F99:F99),0)<$F$15,MIN(($F$15-SUM($F99:F99)),$F$15*$B$95),0)) | H99: =+IF(G99=0,0,+IF(ROUNDUP(SUM($F99:G99),0)<$F$15,MIN(($F$15-SUM($F99:G99)),$F$15*$B$95),0))
A100: =A91 | G100: =+IF(G$15<0,0,G$15*$B$95)/12*G$31 | H100: =+IF(G100=0,0,+IF(ROUNDUP(SUM($G100:G100),0)<$G$15,MIN(($G$15-SUM($G100:G100)),$G$15*$B$95),0))
A101: =A92 | H101: =+IF(H$15<0,0,H$15*$B$95)/12*H$31
A102: Equipamento básico | B102: =+C66 | C102: =SUM(C103:C108) | D102: =SUM(D103:D108) | E102: =SUM(E103:E108) | F102: =SUM(F103:F108) | G102: =SUM(G103:G108) | H102: =SUM(H103:H108)
A103: =A96 | C103: =+IF(C$16<0,0,C$16*$B$102)/12*C$31 | D103: =+IF(AND(C103>0,C16>0),+IF(ROUNDUP(SUM($C103:C103),0)<C16,+C16*$B102*(C$31/12)),C16*$B102*(D$31/12)) | E103: =+IF(D103=0,0,+IF(ROUNDUP(SUM($C103:D103),0)<$C$16,MIN(($C$16-SUM($C103:D103)),+$C$16*$B$102),0)) | F103: =+IF(E103=0,0,+IF(ROUNDUP(SUM($C103:E103),0)<$C$16,MIN(($C$16-SUM($C103:E103)),+$C$16*$B$102),0)) | G103: =+IF(F103=0,0,+IF(ROUNDUP(SUM($C103:F103),0)<$C$16,MIN(($C$16-SUM($C103:F103)),+$C$16*$B$102),0)) | H103: =+IF(G103=0,0,+IF(ROUNDUP(SUM($C103:G103),0)<$C$16,MIN(($C$16-SUM($C103:G103)),+$C$16*$B$102),0))
A104: =A97 | D104: =+IF(D$16<0,0,D$16*$B$102)/12*D$31 | E104: =+IF(D104=0,0,+IF(ROUNDUP(SUM($D104:D104),0)<$D$16,MIN(($D$16-SUM($D104:D104)),+$D$16*$B$102),0)) | F104: =+IF(E104=0,0,+IF(ROUNDUP(SUM($D104:E104),0)<$D$16,MIN(($D$16-SUM($D104:E104)),+$D$16*$B$102),0)) | G104: =+IF(F104=0,0,+IF(ROUNDUP(SUM($D104:F104),0)<$D$16,MIN(($D$16-SUM($D104:F104)),+$D$16*$B$102),0)) | H104: =+IF(G104=0,0,+IF(ROUNDUP(SUM($D104:G104),0)<$D$16,MIN(($D$16-SUM($D104:G104)),+$D$16*$B$102),0))
A105: =A98 | E105: =+IF(E$16<0,0,E$16*$B$102)/12*E$31 | F105: =+IF(E105=0,0,+IF(ROUNDUP(SUM($E105:E105),0)<$E$16,MIN(($E$16-SUM($E105:E105)),+$E$16*$B$102),0)) | G105: =+IF(F105=0,0,+IF(ROUNDUP(SUM($E105:F105),0)<$E$16,MIN(($E$16-SUM($E105:F105)),+$E$16*$B$102),0)) | H105: =+IF(G105=0,0,+IF(ROUNDUP(SUM($E105:G105),0)<$E$16,MIN(($E$16-SUM($E105:G105)),+$E$16*$B$102),0))
A106: =A99 | F106: =+IF(F$16<0,0,F$16*$B$102)/12*F$31 | G106: =+IF(F106=0,0,+IF(ROUNDUP(SUM($F106:F106),0)<$F$16,MIN(($F$16-SUM($F106:F106)),+$F$16*$B$102),0)) | H106: =+IF(G106=0,0,+IF(ROUNDUP(SUM($F106:G106),0)<$F$16,MIN(($F$16-SUM($F106:G106)),+$F$16*$B$102),0))
A107: =A100 | G107: =+IF(G$16<0,0,G$16*$B$102)/12*G$31 | H107: =+IF(G107=0,0,+IF(ROUNDUP(SUM($G107:G107),0)<$G$16,MIN(($G$16-SUM($G107:G107)),+$G$16*$B$102),0))
A108: =A101 | H108: =+IF(H$16<0,0,H$16*$B$102)/12*H$31
A109: Equipamento de transporte | B109: =+C67 | C109: =SUM(C110:C115) | D109: =SUM(D110:D115) | E109: =SUM(E110:E115) | F109: =SUM(F110:F115) | G109: =SUM(G110:G115) | H109: =SUM(H110:H115)
...

Sheet Financiamento
G1: Empresa: | H1: =+Pressupostos!E1
H2: =+Pressupostos!B9
A4: Financiamento
C7: =+VN!C8 | D7: =+VN!D8 | E7: =+VN!E8 | F7: =+VN!F8 | G7: =+VN!G8 | H7: =+VN!H8
A8: Investimento | C8: =Investimento!C29+FundoManeio!C24 | D8: =Investimento!D29+FundoManeio!D24 | E8: =Investimento!E29+FundoManeio!E24 | F8: =Investimento!F29+FundoManeio!F24 | G8: =Investimento!G29+FundoManeio!G24 | H8: =Investimento!H29+FundoManeio!H24
A9: Margem de Segurança | D9: 0 | E9: 0 | F9: 0 | G9: 0 | H9: 0
A10: Necessidades de Financiamento | C10: =+ROUND(C8*(1+C9),0) | D10: =+ROUND(D8*(1+D9),0) | E10: =+ROUND(E8*(1+E9),0) | F10: =+ROUND(F8*(1+F9),0) | G10: =+ROUND(G8*(1+G9),0) | H10: =+ROUND(H8*(1+H9),0)
A13: Fontes de Financiamento | C13: =+C7 | D13: =+D7 | E13: =+E7 | F13: =+F7 | G13: =+G7 | H13: =+H7
A14: Meios Libertos | C14: =IF(+'Cash Flow'!C12>0,'Cash Flow'!C12,0) | D14: =IF(+'Cash Flow'!D12>0,'Cash Flow'!D12,0) | E14: =IF(+'Cash Flow'!E12>0,'Cash Flow'!E12,0) | F14: =IF(+'Cash Flow'!F12>0,'Cash Flow'!F12,0) | G14: =IF(+'Cash Flow'!G12>0,'Cash Flow'!G12,0) | H14: =IF(+'Cash Flow'!H12>0,'Cash Flow'!H12,0)
A15: Capital | C15: =0.25*C10
A16: Outros Instrumentos de Capital
A17: Empréstimos de Sócios
A18: Financiamento Bancário e Outras Inst. Crédito | C18: =+C10-C15-C16-C17-C19 | D18: =0.5*FundoManeio!D24
A19: Subsídios
A20: TOTAL | C20: =SUM(C14:C19) | D20: =SUM(D14:D19) | E20: =SUM(E14:E19) | F20: =SUM(F14:F19) | G20: =SUM(G14:G19) | H20: =SUM(H14:H19)
A22: N.º de Anos Reembolso
A23: Taxa de Juro Associada
A24: N.º Anos de Carência
A26: =+C13
A27: Capital em Dívida (Início Período) | C27: =+C18 | D27: =+C33 | E27: =+D33 | F27: =+E33 | G27: =+F33 | H27: =+G33
A28: Taxa de Juro | C28: =$B$23 | D28: =$B$23 | E28: =$B$23 | F28: =$B$23 | G28: =$B$23 | H28: =$B$23
A29: Juro Anual | C29: =+C27*C28*FSE!F8/12 | D29: =+D27*D28 | E29: =+E27*E28 | F29: =+F27*F28 | G29: =+G27*G28 | H29: =+H27*H28
A30: Reembolso Anual | C30: =IF(B24>=0,0,C27/B22) | D30: =IF(B24>=1,0,IF(C27=0,0,+$C$27/$B$22)) | E30: =IF(B24>=2,0,IF(D33<=0,0,+$C$27/$B$22)) | F30: =IF(B24>=3,0,IF(E33<=0,0,+$C$27/$B$22)) | G30: =IF(B24>=4,0,IF(F33<=0,0,+$C$27/$B$22)) | H30: =IF(B24>=5,0,IF(G33<=0,0,+$C$27/$B$22))
A31: Imposto Selo (4%) | C31: =+C29*0.04 | D31: =+D29*0.04 | E31: =+E29*0.04 | F31: =+F29*0.04 | G31: =+G29*0.04 | H31: =+H29*0.04
A32: Serviço da Dívida | C32: =+C29+C30+C31 | D32: =+D29+D30+D31 | E32: =+E29+E30+E31 | F32: =+F29+F30+F31 | G32: =+G29+G30+G31 | H32: =+H29+H30+H31
A33: Valor em Dívida | C33: =+C27-C30 | D33: =+D27-D30 | E33: =+E27-E30 | F33: =+F27-F30 | G33: =+G27-G30 | H33: =+H27-H30
A35: N.º de Anos Reembolso
A36: Taxa de Juro Associada
A37: N.º Anos de Carência
A39: =+D13
A40: Capital em Dívida (Início Período) | D40: =+D18 | E40: =+D46 | F40: =+E46 | G40: =+F46 | H40: =+G46
A41: Taxa de Juro | D41: =$B$36 | E41: =$B$36 | F41: =$B$36 | G41: =$B$36 | H41: =$B$36
A42: Juro Anual | D42: =+D40*D41 | E42: =+E40*E41 | F42: =+F40*F41 | G42: =+G40*G41 | H42: =+H40*H41
A43: Reembolso Anual | D43: =IF(B37>=0,0,D40/B35) | E43: =IF(B37>=1,0,IF(D46<=0,0,+$D$40/$B$35)) | F43: =IF(B37>=2,0,IF(E46<=0,0,+$D$40/$B$35)) | G43: =IF(B37>=3,0,IF(F46<=0,0,+$D$40/$B$35)) | H43: =IF(B37>=4,0,IF(G46<=0,0,+$D$40/$B$35))
A44: Imposto Selo (4%) | D44: =+D42*0.04 | E44: =+E42*0.04 | F44: =+F42*0.04 | G44: =+G42*0.04 | H44: =+H42*0.04
A45: Serviço da Dívida | D45: =+D42+D43+D44 | E45: =+E42+E43+E44 | F45: =+F42+F43+F44 | G45: =+G42+G43+G44 | H45: =+H42+H43+H44
A46: Valor em Dívida | D46: =+D40-D43 | E46: =+E40-E43 | F46: =+F40-F43 | G46: =+G40-G43 | H46: =+H40-H43
A48: N.º de Anos Reembolso
A49: Taxa de Juro Associada
A50: N.º Anos de Carência
A52: =+E13
A53: Capital em Dívida (Início Período) | E53: =+E18 | F53: =+E59 | G53: =+F59 | H53: =+G59
A54: Taxa de Juro | E54: =$B$49 | F54: =$B$49 | G54: =$B$49 | H54: =$B$49
A55: Juro Anual | E55: =+E53*E54 | F55: =+F53*F54 | G55: =+G53*G54 | H55: =+H53*H54
A56: Reembolso Anual | E56: =IF(B50>=0,0,E53/B48) | F56: =IF(B50>=1,0,IF(E59<=9,0,$E$53/$B$48)) | G56: =IF(B50>=2,0,IF(F59<=9,0,$E$53/$B$48)) | H56: =IF(B50>=3,0,IF(G59<=9,0,$E$53/$B$48))
A57: Imposto Selo (4%) | E57: =+E55*0.04 | F57: =+F55*0.04 | G57: =+G55*0.04 | H57: =+H55*0.04
A58: Serviço da Dívida | E58: =+E55+E56+E57 | F58: =+F55+F56+F57 | G58: =+G55+G56+G57 | H58: =+H55+H56+H57
A59: Valor em Divida | E59: =+E53-E56 | F59: =+F53-F56 | G59: =+G53-G56 | H59: =+H53-H56
A61: N.º de Anos Reembolso
A62: Taxa de Juro Associada
A63: N.º Anos de Carência
A65: =+F13
A66: Capital em Dívida (Início Período) | F66: =+F18 | G66: =+F72 | H66: =+G72
A67: Taxa de Juro | F67: =$B$62 | G67: =$B$62 | H67: =$B$62
A68: Juro Anual | F68: =+F66*F67 | G68: =+G66*G67 | H68: =+H66*H67
A69: Reembolso Anual | F69: =IF(B63>=0,0,F66/B61) | G69: =IF(B63>=1,0,IF(F72<=0,0,$F$66/$B$61)) | H69: =IF(B63>=2,0,IF(G72<=0,0,$F$66/$B$61))
A70: Imposto Selo (4%) | F70: =+F68*0.04 | G70: =+G68*0.04 | H70: =+H68*0.04
A71: Serviço da Dívida | F71: =+F68+F69+F70 | G71: =+G68+G69+G70 | H71: =+H68+H69+H70
A72: Valor em Dívida | F72: =+F66-F69 | G72: =+G66-G69 | H72: =+H66-H69
A74: N.º de Anos Reembolso
A75: Taxa de Juro Associada
A76: N.º Anos de Carência
A78: =+G13
A79: Capital em Dívida (Início Período) | G79: =+G18 | H79: =+G85
A80: Taxa de Juro | G80: =B75 | H80: =B75
A81: Juro Anual | G81: =+G79*G80 | H81: =+H79*H80
A82: Reembolso Anual | G82: =IF(B76>=0,0,G79/B74) | H82: =IF(B76>=1,0,IF(G85<=0,0,$G$79/B74))
A83: Imposto Selo (4%) | G83: =+G81*0.04 | H83: =+H81*0.04
A84: Serviço da Dívida | G84: =+G81+G82+G83 | H84: =+H81+H82+H83
A85: Valor em Dívida | G85: =+G79-G82 | H85: =+H79-H82
A87: N.º de Anos Reembolso
A88: Taxa de Juro Associada
A89: N.º Anos de Carência
A91: =+H13
A92: Capital em Dívida (Início Período) | H92: =+H18
A93: Taxa de Juro | H93: =B88
A94: Juro Anual | H94: =+H92*H93
A95: Reembolso Anual | H95: =IF(B89>=0,0,H92/B87)
A96: Imposto Selo (4%) | H96: =+H94*0.04
A97: Serviço da Dívida | H97: =+H94+H95+H96
A98: Valor em Dívida | H98: =+H92-H95
A101: Capital em Dívida | C101: =+C33+C46+C59+C72+C85+C98 | D101: =+D33+D46+D59+D72+D85+D98 | E101: =+E33+E46+E59+E72+E85+E98 | F101: =+F33+F46+F59+F72+F85+F98 | G101: =+G33+G46+G59+G72+G85+G98 | H101: =+H33+H46+H59+H72+H85+H98
A103: Juros Pagos com Imposto Selo Incluído | C103: =+C29+C42+C55+C68+C81+C94+C31+C44+C57+C70+C83+C96 | D103: =+D29+D42+D55+D68+D81+D94+D31+D44+D57+D70+D83+D96 | E103: =+E29+E42+E55+E68+E81+E94+E31+E44+E57+E70+E83+E96 | F103: =+F29+F42+F55+F68+F81+F94+F31+F44+F57+F70+F83+F96 | G103: =+G29+G42+G55+G68+G81+G94+G31+G44+G57+G70+G83+G96 | H103: =+H29+H42+H55+H68+H81+H94+H31+H44+H57+H70+H83+H96
A104: Reembolso | C104: =+C30+C43+C56+C69+C82+C95 | D104: =+D30+D43+D56+D69+D82+D95 | E104: =+E30+E43+E56+E69+E82+E95 | F104: =+F30+F43+F56+F69+F82+F95 | G104: =+G30+G43+G56+G69+G82+G95 | H104: =+H30+H43+H56+H69+H82+H95

Sheet Ponto Crítico
F1: Empresa: | G1: =+Pressupostos!E1
G2: =+Pressupostos!B9
A4: Ponto Crítico Operacional Previsional
B7: =+VN!C8 | C7: =+VN!D8 | D7: =+VN!E8 | E7: =+VN!F8 | F7: =+VN!G8 | G7: =+VN!H8
A8: =DR!A8 | B8: =DR!B8 | C8: =DR!C8 | D8: =DR!D8 | E8: =DR!E8 | F8: =DR!F8 | G8: =DR!G8
A9: =DR!A11 | B9: =DR!B11 | C9: =DR!C11 | D9: =DR!D11 | E9: =DR!E11 | F9: =DR!F11 | G9: =DR!G11
A10: CMVMC | B10: =DR!B13 | C10: =DR!C13 | D10: =DR!D13 | E10: =DR!E13 | F10: =DR!F13 | G10: =DR!G13
A11: FSE Variáveis | B11: =FSE!F47 | C11: =FSE!G47 | D11: =FSE!H47 | E11: =FSE!I47 | F11: =FSE!J47 | G11: =FSE!K47
A12: Margem Bruta de Contribuição | B12: =B8+B9-B10-B11 | C12: =C8+C9-C10-C11 | D12: =D8+D9-D10-D11 | E12: =E8+E9-E10-E11 | F12: =F8+F9-F10-F11 | G12: =G8+G9-G10-G11
A13: Ponto Crítico | B13: =IF(B8>0,(FSE!F45+DR!B15+DR!B24+DR!B25+DR!B18)/(B12/'Ponto Crítico'!B8),"") | C13: =IF(C8>0,(FSE!G45+DR!C15+DR!C24+DR!C25+DR!C18)/(C12/'Ponto Crítico'!C8),"") | D13: =IF(D8>0,(FSE!H45+DR!D15+DR!D24+DR!D25+DR!D18)/(D12/'Ponto Crítico'!D8),"") | E13: =IF(E8>0,(FSE!I45+DR!E15+DR!E24+DR!E25+DR!E18)/(E12/'Ponto Crítico'!E8),"") | F13: =IF(F8>0,(FSE!J45+DR!F15+DR!F24+DR!F25+DR!F18)/(F12/'Ponto Crítico'!F8),"") | G13: =IF(G8>0,(FSE!K45+DR!G15+DR!G24+DR!G25+DR!G18)/(G12/'Ponto Crítico'!G8),"")

Sheet DR
F1: Empresa: | G1: =+Pressupostos!E1
G2: =+Pressupostos!B9
A4: Demonstração de Resultados Previsional
B7: =+VN!C8 | C7: =+VN!D8 | D7: =+VN!E8 | E7: =+VN!F8 | F7: =+VN!G8 | G7: =+VN!H8
A8: Vendas e Serviços Prestados | B8: =+VN!C80 | C8: =+VN!D80 | D8: =+VN!E80 | E8: =+VN!F80 | F8: =+VN!G80 | G8: =+VN!H80
A9: Subsídios à Exploração
A10: Ganhos/Perdas Imputados de Subsidiárias, Associadas e Empreendimentos Conjuntos
A11: Variação nos Inventários da Produção
A12: Trabalhos para a Própria Entidade
A13: CMVMC | B13: =+CMVMC!C16 | C13: =+CMVMC!D16 | D13: =+CMVMC!E16 | E13: =+CMVMC!F16 | F13: =+CMVMC!G16 | G13: =+CMVMC!H16
A14: Fornecimento e Serviços Externos | B14: =+FSE!F43 | C14: =+FSE!G43 | D14: =+FSE!H43 | E14: =+FSE!I43 | F14: =+FSE!J43 | G14: =+FSE!K43
A15: Gastos com o Pessoal | B15: =+'Gastos com Pessoal'!D94 | C15: =+'Gastos com Pessoal'!E94 | D15: =+'Gastos com Pessoal'!F94 | E15: =+'Gastos com Pessoal'!G94 | F15: =+'Gastos com Pessoal'!H94 | G15: =+'Gastos com Pessoal'!I94
A16: Imparidade de Inventários (Perdas/Reversões)
A17: Imparidade de Dívidas a Receber (Perdas/Reversões) | B17: =+VN!C87 | C17: =+VN!D87 | D17: =+VN!E87 | E17: =+VN!F87 | F17: =+VN!G87 | G17: =+VN!H87
A18: Provisões (Aumentos/Reduções)
A19: Imparidade de Investimentos Não Depreciáveis/Amortizáveis (Perdas/Reversões)
A20: Aumentos/Reduções de Justo Valor
A21: Outros Rendimentos e Ganhos
A22: Outros Gastos e Perdas
A23: EBITDA (Resultado antes de Depreciações, Gastos de Financiamento e Impostos) | B23: =+B8+B9+B10+B11+B12-B13-B14-B15-B16-B17-B18-B19-B20+B21-B22 | C23: =+C8+C9+C10+C11+C12-C13-C14-C15-C16-C17-C18-C19-C20+C21-C22 | D23: =+D8+D9+D10+D11+D12-D13-D14-D15-D16-D17-D18-D19-D20+D21-D22 | E23: =+E8+E9+E10+E11+E12-E13-E14-E15-E16-E17-E18-E19-E20+E21-E22 | F23: =+F8+F9+F10+F11+F12-F13-F14-F15-F16-F17-F18-F19-F20+F21-F22 | G23: =+G8+G9+G10+G11+G12-G13-G14-G15-G16-G17-G18-G19-G20+G21-G22
A24: Gastos/Reversões de Depreciação e Amortização | B24: =+Investimento!C168 | C24: =+Investimento!D168 | D24: =+Investimento!E168 | E24: =+Investimento!F168 | F24: =+Investimento!G168 | G24: =+Investimento!H168
A25: Imparidade de Ativos Depreciáveis/Amortizáveis (Perdas/Reversões)
A26: EBIT (Resultado Operacional) | B26: =+B23-B24-B25 | C26: =+C23-C24-C25 | D26: =+D23-D24-D25 | E26: =+E23-E24-E25 | F26: =+F23-F24-F25 | G26: =+G23-G24-G25
A27: Juros e Rendimentos Similares Obtidos | B27: =+IF(PlanoFinanceiro!C29>0,PlanoFinanceiro!C29*Pressupostos!$B$31,0) | C27: =+IF(PlanoFinanceiro!D29>0,PlanoFinanceiro!D29*Pressupostos!$B$31,0) | D27: =+IF(PlanoFinanceiro!E29>0,PlanoFinanceiro!E29*Pressupostos!$B$31,0) | E27: =+IF(PlanoFinanceiro!F29>0,PlanoFinanceiro!F29*Pressupostos!$B$31,0) | F27: =+IF(PlanoFinanceiro!G29>0,PlanoFinanceiro!G29*Pressupostos!$B$31,0) | G27: =+IF(PlanoFinanceiro!H29>0,PlanoFinanceiro!H29*Pressupostos!$B$31,0)
A28: Juros e Gastos Similares Suportados | B28: =Financiamento!C103+IF(PlanoFinanceiro!C29<0,-PlanoFinanceiro!C29*Pressupostos!$B$32,0) | C28: =Financiamento!D103+IF(PlanoFinanceiro!D29<0,-PlanoFinanceiro!D29*Pressupostos!$B$32,0) | D28: =Financiamento!E103+IF(PlanoFinanceiro!E29<0,-PlanoFinanceiro!E29*Pressupostos!$B$32,0) | E28: =Financiamento!F103+IF(PlanoFinanceiro!F29<0,-PlanoFinanceiro!F29*Pressupostos!$B$32,0) | F28: =Financiamento!G103+IF(PlanoFinanceiro!G29<0,-PlanoFinanceiro!G29*Pressupostos!$B$32,0) | G28: =Financiamento!H103+IF(PlanoFinanceiro!H29<0,-PlanoFinanceiro!H29*Pressupostos!$B$32,0)
A29: RESULTADO ANTES DE IMPOSTOS | B29: =+B26+B27-B28 | C29: =+C26+C27-C28 | D29: =+D26+D27-D28 | E29: =+E26+E27-E28 | F29: =+F26+F27-F28 | G29: =+G26+G27-G28
A30: Imposto sobre o Rendimento do Período | B30: =IF(B29>0,B29*Pressupostos!$B$29,0) | C30: =IF(C29+C32<0,0,(C29+C32)*Pressupostos!$B$29) | D30: =IF(D29+D32<0,0,(D29+D32)*Pressupostos!$B$29) | E30: =IF(E29+E32<0,0,(E29+E32)*Pressupostos!$B$29) | F30: =IF(F29+F32<0,0,(F29+F32)*Pressupostos!$B$29) | G30: =IF(G29+G32<0,0,(G29+G32)*Pressupostos!$B$29)
A31: RESULTADO LÍQUIDO DO PERÍODO | B31: =+B29-B30 | C31: =+C29-C30 | D31: =+D29-D30 | E31: =+E29-E30 | F31: =+F29-F30 | G31: =+G29-G30
C32: =IF(B31<0,B31,0) | D32: =IF(C31+C32<0,C31+C32,0) | E32: =IF(D31+D32<0,D31+D32,0) | F32: =IF(E31+E32<0,E31+E32,0) | G32: =IF(F31+F32<0,F31+F32,0)

Sheet Cash Flow
G1: Empresa: | H1: =+Pressupostos!E1
H2: =+Pressupostos!B9
A4: Mapa de Cash Flows Operacionais
C7: =+VN!C8 | D7: =+VN!D8 | E7: =+VN!E8 | F7: =+VN!F8 | G7: =+VN!G8 | H7: =+VN!H8
A8: Meios Libertos do Projeto
A9: Resultados Operacionais (EBIT) x (1-IRC) | C9: =+DR!B26*(1-Pressupostos!$B$29) | D9: =+DR!C26*(1-Pressupostos!$B$29) | E9: =+DR!D26*(1-Pressupostos!$B$29) | F9: =+DR!E26*(1-Pressupostos!$B$29) | G9: =+DR!F26*(1-Pressupostos!$B$29) | H9: =+DR!G26*(1-Pressupostos!$B$29)
A10: Depreciações e Amortizações | C10: =+DR!B24 | D10: =+DR!C24 | E10: =+DR!D24 | F10: =+DR!E24 | G10: =+DR!F24 | H10: =+DR!G24
A11: Provisões do Exercício | C11: =+DR!B25 | D11: =+DR!C25 | E11: =+DR!D25 | F11: =+DR!E25 | G11: =+DR!F25 | H11: =+DR!G25
C12: =SUM(C9:C11) | D12: =SUM(D9:D11) | E12: =SUM(E9:E11) | F12: =SUM(F9:F11) | G12: =SUM(G9:G11) | H12: =SUM(H9:H11)
A13: Investim./Desinvest. em Fundo Maneio
A14: Fundo de Maneio | C14: =-FundoManeio!C24 | D14: =-FundoManeio!D24 | E14: =-FundoManeio!E24 | F14: =-FundoManeio!F24 | G14: =-FundoManeio!G24 | H14: =-FundoManeio!H24
A16: CASH FLOW de Exploração | C16: =+SUM(C12:C14) | D16: =+SUM(D12:D14) | E16: =+SUM(E12:E14) | F16: =+SUM(F12:F14) | G16: =+SUM(G12:G14) | H16: =+SUM(H12:H14)
A18: Investim./Desinvest. em Capital Fixo
A19: Capital Fixo | C19: =-Investimento!C29 | D19: =-Investimento!D29 | E19: =-Investimento!E29 | F19: =-Investimento!F29 | G19: =-Investimento!G29 | H19: =-Investimento!H29
A21: Free Cash Flow | C21: =+C12+C14+C19 | D21: =+D12+D14+D19 | E21: =+E12+E14+E19 | F21: =+F12+F14+F19 | G21: =+G12+G14+G19 | H21: =+H12+H14+H19
A23: CASH FLOW Acumulado | C23: =+SUM(C21) | D23: =+SUM($C$21:D21) | E23: =+SUM($C$21:E21) | F23: =+SUM($C$21:F21) | G23: =+SUM($C$21:G21) | H23: =+SUM($C$21:H21)

Sheet PlanoFinanceiro
G1: Empresa: | H1: =+Pressupostos!E1
H2: =+Pressupostos!B9
A4: Plano de Financiamento
C7: =+VN!C8 | D7: =+VN!D8 | E7: =+VN!E8 | F7: =+VN!F8 | G7: =+VN!G8 | H7: =+VN!H8
A8: ORIGENS DE FUNDOS
A9: Meios Libertos Brutos | C9: =+DR!B26+DR!B24+DR!B25+DR!B17 | D9: =+DR!C26+DR!C24+DR!C25+DR!C17 | E9: =+DR!D26+DR!D24+DR!D25+DR!D17 | F9: =+DR!E26+DR!E24+DR!E25+DR!E17 | G9: =+DR!F26+DR!F24+DR!F25+DR!F17 | H9: =+DR!G26+DR!G24+DR!G25+DR!G17
A10: Capital Social (Entrada de Fundos) | C10: =+Financiamento!C15 | D10: =+Financiamento!D15 | E10: =+Financiamento!E15 | F10: =+Financiamento!F15 | G10: =+Financiamento!G15 | H10: =+Financiamento!H15
A11: Outros Instrumentos de Capital | C11: =+Financiamento!C16+Financiamento!C17+Financiamento!C19 | D11: =+Financiamento!D16+Financiamento!D17+Financiamento!D19 | E11: =+Financiamento!E16+Financiamento!E17+Financiamento!E19 | F11: =+Financiamento!F16+Financiamento!F17+Financiamento!F19 | G11: =+Financiamento!G16+Financiamento!G17+Financiamento!G19 | H11: =+Financiamento!H16+Financiamento!H17+Financiamento!H19
A12: Empréstimos Obtidos | C12: =+Financiamento!C18 | D12: =+Financiamento!D18 | E12: =+Financiamento!E18 | F12: =+Financiamento!F18 | G12: =+Financiamento!G18 | H12: =+Financiamento!H18
A13: Desinvest. em Capital Fixo
A14: Desinvest. em FMN | C14: =+IF(FundoManeio!C24<0,-FundoManeio!C24,0) | D14: =+IF(FundoManeio!D24<0,-FundoManeio!D24,0) | E14: =+IF(FundoManeio!E24<0,-FundoManeio!E24,0) | F14: =+IF(FundoManeio!F24<0,-FundoManeio!F24,0) | G14: =+IF(FundoManeio!G24<0,-FundoManeio!G24,0) | H14: =+IF(FundoManeio!H24<0,-FundoManeio!H24,0)
A15: Proveitos Financeiros | C15: =+DR!B27 | D15: =+DR!C27 | E15: =+DR!D27 | F15: =+DR!E27 | G15: =+DR!F27 | H15: =+DR!G27
A17: Total das Origens | C17: =+SUM(C9:C16) | D17: =+SUM(D9:D16) | E17: =+SUM(E9:E16) | F17: =+SUM(F9:F16) | G17: =+SUM(G9:G16) | H17: =+SUM(H9:H16)
A18: APLICAÇÕES DE FUNDOS
A19: Inv. Capital Fixo | C19: =+Investimento!C29 | D19: =+Investimento!D29 | E19: =+Investimento!E29 | F19: =+Investimento!F29 | G19: =+Investimento!G29 | H19: =+Investimento!H29
A20: Inv. Fundo de Maneio | C20: =+IF(FundoManeio!C24>0,FundoManeio!C24,0) | D20: =+IF(FundoManeio!D24>0,FundoManeio!D24,0) | E20: =+IF(FundoManeio!E24>0,FundoManeio!E24,0) | F20: =+IF(FundoManeio!F24>0,FundoManeio!F24,0) | G20: =+IF(FundoManeio!G24>0,FundoManeio!G24,0) | H20: =+IF(FundoManeio!H24>0,FundoManeio!H24,0)
A21: Imposto sobre os Lucros | D21: =+DR!B30 | E21: =+DR!C30 | F21: =+DR!D30 | G21: =+DR!E30 | H21: =+DR!F30
A22: Pagamento de Dividendos
A23: Reembolso de Empréstimos | C23: =+Financiamento!C104 | D23: =+Financiamento!D104 | E23: =+Financiamento!E104 | F23: =+Financiamento!F104 | G23: =+Financiamento!G104 | H23: =+Financiamento!H104
A24: Encargos Financeiros | C24: =+DR!B28 | D24: =+DR!C28 | E24: =+DR!D28 | F24: =+DR!E28 | G24: =+DR!F28 | H24: =+DR!G28
A26: Total das Aplicações | C26: =+SUM(C19:C25) | D26: =+SUM(D19:D25) | E26: =+SUM(E19:E25) | F26: =+SUM(F19:F25) | G26: =+SUM(G19:G25) | H26: =+SUM(H19:H25)
A27: Saldo de Tesouraria Anual | C27: =+C17-C26 | D27: =+D17-D26 | E27: =+E17-E26 | F27: =+F17-F26 | G27: =+G17-G26 | H27: =+H17-H26
A28: Saldo de Tesouraria Acumulado | C28: =+C27 | D28: =+C28+D27 | E28: =+D28+E27 | F28: =+E28+F27 | G28: =+F28+G27 | H28: =+G28+H27
A29: Aplicações/Empréstimo Curto Prazo | C29: 0 | D29: 0 | E29: 0 | F29: 7.2759576e-12 | G29: 7.2759576e-12 | H29: 1.4551915e-11
A30: Soma Controlo | C30: =+C28-C29 | D30: =+D28-D29 | E30: =+E28-E29 | F30: =+F28-F29 | G30: =+G28-G29 | H30: =+H28-H29

Sheet Balanço
G1: Empresa: | H1: =+Pressupostos!E1
H2: =+Pressupostos!B9
A4: Balanço Previsional
C7: =+VN!C8 | D7: =+VN!D8 | E7: =+VN!E8 | F7: =+VN!F8 | G7: =+VN!G8 | H7: =+VN!H8
A8: ATIVO
A9: Ativo Não Corrente | C9: =SUM(C10:C13) | D9: =SUM(D10:D13) | E9: =SUM(E10:E13) | F9: =SUM(F10:F13) | G9: =SUM(G10:G13) | H9: =SUM(H10:H13)
A10: Ativos Fixos Tangíveis | C10: =+Investimento!C180 | D10: =+Investimento!D180 | E10: =+Investimento!E180 | F10: =+Investimento!F180 | G10: =+Investimento!G180 | H10: =+Investimento!H180
A11: Propriedades de Investimento | C11: =+Investimento!C179 | D11: =+Investimento!D179 | E11: =+Investimento!E179 | F11: =+Investimento!F179 | G11: =+Investimento!G179 | H11: =+Investimento!H179
A12: Ativos Intangíveis | C12: =+Investimento!C181 | D12: =+Investimento!D181 | E12: =+Investimento!E181 | F12: =+Investimento!F181 | G12: =+Investimento!G181 | H12: =+Investimento!H181
A13: Investimentos Financeiros
A15: Ativo Corrente | C15: =SUM(C16:C22) | D15: =SUM(D16:D22) | E15: =SUM(E16:E22) | F15: =SUM(F16:F22) | G15: =SUM(G16:G22) | H15: =SUM(H16:H22)
A16: Inventários | C16: =+FundoManeio!C11 | D16: =+FundoManeio!D11 | E16: =+FundoManeio!E11 | F16: =+FundoManeio!F11 | G16: =+FundoManeio!G11 | H16: =+FundoManeio!H11
A17: Clientes | C17: =+FundoManeio!C10-VN!C87 | D17: =+FundoManeio!D10-SUM(VN!C87:D87) | E17: =+FundoManeio!E10-SUM(VN!C87:E87) | F17: =+FundoManeio!F10-SUM(VN!C87:F87) | G17: =+FundoManeio!G10-SUM(VN!C87:G87) | H17: =+FundoManeio!H10-SUM(VN!C87:H87)
A18: Estado e Outros Entes Públicos | C18: =+FundoManeio!C12 | D18: =+FundoManeio!D12 | E18: =+FundoManeio!E12 | F18: =+FundoManeio!F12 | G18: =+FundoManeio!G12 | H18: =+FundoManeio!H12
A19: Acionistas/Sócios
A20: Outras Contas a Receber
A21: Diferimentos
A22: Caixa e Depósitos Bancários | C22: =+IF(PlanoFinanceiro!C29>0,PlanoFinanceiro!C29,0)+FundoManeio!C9 | D22: =+IF(PlanoFinanceiro!D29>0,PlanoFinanceiro!D29,0)+FundoManeio!D9 | E22: =+IF(PlanoFinanceiro!E29>0,PlanoFinanceiro!E29,0)+FundoManeio!E9 | F22: =+IF(PlanoFinanceiro!F29>0,PlanoFinanceiro!F29,0)+FundoManeio!F9 | G22: =+IF(PlanoFinanceiro!G29>0,PlanoFinanceiro!G29,0)+FundoManeio!G9 | H22: =+IF(PlanoFinanceiro!H29>0,PlanoFinanceiro!H29,0)+FundoManeio!H9
A23: TOTAL ATIVO | C23: =+C15+C9 | D23: =+D15+D9 | E23: =+E15+E9 | F23: =+F15+F9 | G23: =+G15+G9 | H23: =+H15+H9
A25: CAPITAL PRÓPRIO
A26: Capital realizado | C26: =+Financiamento!C15 | D26: =+C26+Financiamento!D15 | E26: =+D26+Financiamento!E15 | F26: =+E26+Financiamento!F15 | G26: =+F26+Financiamento!G15 | H26: =+G26+Financiamento!H15
A27: Ações (Quotas Próprias)
A28: Outros Instrumentos de Capital Próprio | C28: =+Financiamento!C16 | D28: =+C28+Financiamento!D16 | E28: =+D28+Financiamento!E16 | F28: =+E28+Financiamento!F16 | G28: =+F28+Financiamento!G16 | H28: =+G28+Financiamento!H16
A29: Reservas | D29: =+C32-PlanoFinanceiro!D22 | E29: =+D29+D32-PlanoFinanceiro!E22 | F29: =+E29+E32-PlanoFinanceiro!F22 | G29: =+F29+F32-PlanoFinanceiro!G22 | H29: =+G29+G32-PlanoFinanceiro!H22
A30: Excedentes de Revalorização
A31: Outras Variações no Capital Próprio | C31: =+Financiamento!C19 | D31: =+C31+Financiamento!D19 | E31: =+D31+Financiamento!E19 | F31: =+E31+Financiamento!F19 | G31: =+F31+Financiamento!G19 | H31: =+G31+Financiamento!H19
A32: Resultado Líquido do Período | C32: =+DR!B31 | D32: =+DR!C31 | E32: =+DR!D31 | F32: =+DR!E31 | G32: =+DR!F31 | H32: =+DR!G31
A33: TOTAL DO CAPITAL PRÓPRIO | C33: =SUM(C26:C32) | D33: =SUM(D26:D32) | E33: =SUM(E26:E32) | F33: =SUM(F26:F32) | G33: =SUM(G26:G32) | H33: =SUM(H26:H32)
A35: PASSIVO
A37: Passivo Não Corrente | C37: =SUM(C38:C40) | D37: =SUM(D38:D40) | E37: =SUM(E38:E40) | F37: =SUM(F38:F40) | G37: =SUM(G38:G40) | H37: =SUM(H38:H40)
A38: Provisões
A39: Financiamentos Obtidos | C39: =+Financiamento!C101 | D39: =+Financiamento!D101 | E39: =+Financiamento!E101 | F39: =+Financiamento!F101 | G39: =+Financiamento!G101 | H39: =+Financiamento!H101
A40: Outras Contas a Pagar
A42: Passivo Corrente | C42: =SUM(C43:C47) | D42: =SUM(D43:D47) | E42: =SUM(E43:E47) | F42: =SUM(F43:F47) | G42: =SUM(G43:G47) | H42: =SUM(H43:H47)
A43: Fornecedores | C43: =+FundoManeio!C17 | D43: =+FundoManeio!D17 | E43: =+FundoManeio!E17 | F43: =+FundoManeio!F17 | G43: =+FundoManeio!G17 | H43: =+FundoManeio!H17
A44: Estado e Outros Entes Públicos | C44: =+FundoManeio!C18+DR!B30 | D44: =+FundoManeio!D18+DR!C30 | E44: =+FundoManeio!E18+DR!D30 | F44: =+FundoManeio!F18+DR!E30 | G44: =+FundoManeio!G18+DR!F30 | H44: =+FundoManeio!H18+DR!G30
A45: Acionistas/Sócios | C45: =+Financiamento!C17 | D45: =+C45+Financiamento!D17 | E45: =+D45+Financiamento!E17 | F45: =+E45+Financiamento!F17 | G45: =+F45+Financiamento!G17 | H45: =+G45+Financiamento!H17
A46: Financiamentos Obtidos | C46: =+IF(PlanoFinanceiro!C29<0,-PlanoFinanceiro!C29,0) | D46: =+IF(PlanoFinanceiro!D29<0,-PlanoFinanceiro!D29,0) | E46: =+IF(PlanoFinanceiro!E29<0,-PlanoFinanceiro!E29,0) | F46: =+IF(PlanoFinanceiro!F29<0,-PlanoFinanceiro!F29,0) | G46: =+IF(PlanoFinanceiro!G29<0,-PlanoFinanceiro!G29,0) | H46: =+IF(PlanoFinanceiro!H29<0,-PlanoFinanceiro!H29,0)
A47: Outras Contas a Pagar
A49: TOTAL PASSIVO | C49: =+C42+C37 | D49: =+D42+D37 | E49: =+E42+E37 | F49: =+F42+F37 | G49: =+G42+G37 | H49: =+H42+H37
A51: TOTAL PASSIVO + CAPITAIS PRÓPRIOS | C51: =+C49+C33 | D51: =+D49+D33 | E51: =+E49+E33 | F51: =+F49+F33 | G51: =+G49+G33 | H51: =+H49+H33
C53: =+C23-C51 | D53: =+D23-D51 | E53: =+E23-E51 | F53: =+F23-F51 | G53: =+G23-G51 | H53: =+H23-H51
D54: =+D53-C53 | E54: =+E53-D53 | F54: =+F53-E53 | G54: =+G53-F53 | H54: =+H53-G53

Sheet Indicadores
F1: =+VN!G1 | G1: =+Pressupostos!E1
A4: Principais Indicadores
A6: INDICADORES ECONÓMICOS | B6: =+VN!C8 | C6: =+VN!D8 | D6: =+VN!E8 | E6: =+VN!F8 | F6: =+VN!G8 | G6: =+VN!H8
A7: Taxa de Crescimento do Negócio | C7: =+(DR!C8/DR!B8)-1 | D7: =+(DR!D8/DR!C8)-1 | E7: =+(DR!E8/DR!D8)-1 | F7: =+(DR!F8/DR!E8)-1 | G7: =+(DR!G8/DR!F8)-1
A8: Rendibilidade Líquida sobre as Vendas | B8: =DR!B31/DR!B8 | C8: =DR!C31/DR!C8 | D8: =DR!D31/DR!D8 | E8: =DR!E31/DR!E8 | F8: =DR!F31/DR!F8 | G8: =DR!G31/DR!G8
A10: INDICADORES ECONÓMICO-FINANCEIROS | B10: =+B6 | C10: =+C6 | D10: =+D6 | E10: =+E6 | F10: =+F6 | G10: =+G6
A11: Return On Investment (ROI) | B11: =DR!B31/Balanço!C23 | C11: =DR!C31/Balanço!D23 | D11: =DR!D31/Balanço!E23 | E11: =DR!E31/Balanço!F23 | F11: =DR!F31/Balanço!G23 | G11: =DR!G31/Balanço!H23
A12: Rendibilidade do Ativo | B12: =+DR!B26/Balanço!C23 | C12: =+DR!C26/Balanço!D23 | D12: =+DR!D26/Balanço!E23 | E12: =+DR!E26/Balanço!F23 | F12: =+DR!F26/Balanço!G23 | G12: =+DR!G26/Balanço!H23
A13: Rotação do Ativo | B13: =DR!B8/Balanço!C23 | C13: =DR!C8/Balanço!D23 | D13: =DR!D8/Balanço!E23 | E13: =DR!E8/Balanço!F23 | F13: =DR!F8/Balanço!G23 | G13: =DR!G8/Balanço!H23
A14: Rendibilidade dos Capitais Próprios (ROE) | B14: =+DR!B31/Balanço!C33 | C14: =+DR!C31/Balanço!D33 | D14: =+DR!D31/Balanço!E33 | E14: =+DR!E31/Balanço!F33 | F14: =+DR!F31/Balanço!G33 | G14: =+DR!G31/Balanço!H33
A16: INDICADORES FINANCEIROS | B16: =+B6 | C16: =+C6 | D16: =+D6 | E16: =+E6 | F16: =+F6 | G16: =+G6
A17: Autonomia Financeira | B17: =Balanço!C33/Balanço!C23 | C17: =Balanço!D33/Balanço!D23 | D17: =Balanço!E33/Balanço!E23 | E17: =Balanço!F33/Balanço!F23 | F17: =Balanço!G33/Balanço!G23 | G17: =Balanço!H33/Balanço!H23
A18: Solvabilidade Total | B18: =Balanço!C23/Balanço!C49 | C18: =Balanço!D23/Balanço!D49 | D18: =Balanço!E23/Balanço!E49 | E18: =Balanço!F23/Balanço!F49 | F18: =Balanço!G23/Balanço!G49 | G18: =Balanço!H23/Balanço!H49
A19: Cobertura dos Encargos Financeiros | B19: =+DR!B26/DR!B28 | C19: =+DR!C26/DR!C28 | D19: =+DR!D26/DR!D28 | E19: =+DR!E26/DR!E28 | F19: =+DR!F26/DR!F28 | G19: =+DR!G26/DR!G28
A21: INDICADORES DE LIQUIDEZ | B21: =+B6 | C21: =+C6 | D21: =+D6 | E21: =+E6 | F21: =+F6 | G21: =+G6
A22: Liquidez Corrente | B22: =Balanço!C15/Balanço!C42 | C22: =Balanço!D15/Balanço!D42 | D22: =Balanço!E15/Balanço!E42 | E22: =Balanço!F15/Balanço!F42 | F22: =Balanço!G15/Balanço!G42 | G22: =Balanço!H15/Balanço!H42
A23: Liquidez Reduzida | B23: =(Balanço!C17+Balanço!C18+Balanço!C19+Balanço!C20+Balanço!C21+Balanço!C22)/Balanço!C42 | C23: =(Balanço!D17+Balanço!D18+Balanço!D19+Balanço!D20+Balanço!D21+Balanço!D22)/Balanço!D42 | D23: =(Balanço!E17+Balanço!E18+Balanço!E19+Balanço!E20+Balanço!E21+Balanço!E22)/Balanço!E42 | E23: =(Balanço!F17+Balanço!F18+Balanço!F19+Balanço!F20+Balanço!F21+Balanço!F22)/Balanço!F42 | F23: =(Balanço!G17+Balanço!G18+Balanço!G19+Balanço!G20+Balanço!G21+Balanço!G22)/Balanço!G42 | G23: =(Balanço!H17+Balanço!H18+Balanço!H19+Balanço!H20+Balanço!H21+Balanço!H22)/Balanço!H42
A25: INDICADORES DE RISCO DE NEGÓCIO | B25: =+B6 | C25: =+C6 | D25: =+D6 | E25: =+E6 | F25: =+F6 | G25: =+G6
A26: Margem Bruta | B26: =DR!B8-DR!B11-DR!B13-DR!B14 | C26: =DR!C8-DR!C11-DR!C13-DR!C14 | D26: =DR!D8-DR!D11-DR!D13-DR!D14 | E26: =DR!E8-DR!E11-DR!E13-DR!E14 | F26: =DR!F8-DR!F11-DR!F13-DR!F14 | G26: =DR!G8-DR!G11-DR!G13-DR!G14
A27: Grau de Alavanca Operacional | B27: =+B26/DR!B26 | C27: =+C26/DR!C26 | D27: =+D26/DR!D26 | E27: =+E26/DR!E26 | F27: =+F26/DR!F26 | G27: =+G26/DR!G26
A28: Grau de Alavanca Financeira | B28: =+DR!B26/DR!B29 | C28: =+DR!C26/DR!C29 | D28: =+DR!D26/DR!D29 | E28: =+DR!E26/DR!E29 | F28: =+DR!F26/DR!F29 | G28: =+DR!G26/DR!G29

Sheet Avaliação
H1: =+VN!G1 | I1: =+Pressupostos!E1
A4: Avaliação do Projeto / Empresa
A7: Na Perspetiva do Investimento (pré-financiamento = 100% CP) | C7: =+C27 | D7: =+D27 | E7: =+E27 | F7: =+F27 | G7: =+G27 | H7: =+H27 | I7: =+I27 | L7: CF | M7: CF Acum
J8: ' + 1. ou + 2. Por defeito = 2. | K8: Ano 0 | L8: =+C14 | M8: =+L8 | N8: =IF(M8>0,M8/L8*12)
A9: Free Cash Flow to Firm | C9: =+C29 | D9: =+D29 | E9: =+E29 | F9: =+F29 | G9: =+G29 | H9: =+H29 | I9: =+N20 | K9: Ano 1 | L9: =+D14 | M9: =+M8+L9 | N9: =IF(M9>0,M9/L9*12)
K10: Ano 2 | L10: =+E14 | M10: =+M9+L10 | N10: =IF(M10>0,M10/L10*12)
A11: Taxa de Atualização Rcp = Ru = RF+Bu*(Rm-Rf) | C11: =+C70 | D11: =+D70 | E11: =+E70 | F11: =+F70 | G11: =+G70 | H11: =+H70 | I11: =+I70 | K11: Ano 3 | L11: =+F14 | M11: =+M10+L11 | N11: =IF(M11>0,M11/L11*12)
A12: Fator de Atualização | C12: 1 | D12: =+C12*(1+D11) | E12: =+D12*(1+E11) | F12: =+E12*(1+F11) | G12: =+F12*(1+G11) | H12: =+G12*(1+H11) | I12: =+H12 | K12: Ano 4 | L12: =+G14 | M12: =+M11+L12 | N12: =IF(M12>0,M12/L12*12)
K13: Ano 5 | L13: =+H14 | M13: =+M12+L13 | N13: =IF(M13>0,M13/L13*12)
A14: Fluxos Atualizados | C14: =+C9/C12 | D14: =+D9/D12 | E14: =+E9/E12 | F14: =+F9/F12 | G14: =+G9/G12 | H14: =+H9/H12 | I14: =+I9/I12
A16: Fluxos Atualizados Acumulados | C16: =+C14 | D16: =+C16+D14 | E16: =+D16+E14 | F16: =+E16+F14 | G16: =+F16+G14 | H16: =+G16+H14+I14 | I16: ***
K17: Valor Residual ano N
A18: Valor Atual Líquido (VAL) | C18: =+I16 | K18: 1. PERPETUIDADE a crescer à taxa g em N+1 | N18: =($H$9*(1+Pressupostos!$B$38))/(Avaliação!$I$11-Pressupostos!$B$38)
K19: ou
A20: Taxa Interna de Rendibilidade | C20: =IRR(C9:I9,0.1) | K20: 2.Ativo não depreciado + F.Maneio | N20: =(+Balanço!$H$9+FundoManeio!$H$22)
A22: Pay Back Period (Arred. Ano Inteiro) | B22: Anos | C22: =COUNTIF(N8:N13,"falso") | D22: Meses | J22: Se versão excell for em inglês, meter na fórmula do Preríodo de Recuperação, o termo "false" em vez de "falso"
E23: Cálc. Manual
A27: Na Perspetiva do Investimento (pós-financiamento) Taxa Atualização=Custo Médio Ponderado do Capital - wacc) | C27: =+VN!C8 | D27: =+VN!D8 | E27: =+VN!E8 | F27: =+VN!F8 | G27: =+VN!G8 | H27: =+VN!H8 | I27: =+H27+1 | L27: CF | M27: CF Acum
J28: ' + 1. ou + 2. Por defeito = 2. | K28: Ano 0 | L28: =+C34 | M28: =+L28 | N28: =IF(M28>0,M28/L28*12)
A29: Free Cash Flow to Firm | C29: =+'Cash Flow'!C21 | D29: =+'Cash Flow'!D21 | E29: =+'Cash Flow'!E21 | F29: =+'Cash Flow'!F21 | G29: =+'Cash Flow'!G21 | H29: =+'Cash Flow'!H21 | I29: =+N39 | K29: Ano 1 | L29: =+D34 | M29: =+M28+L29 | N29: =IF(M29>0,M29/L29*12)
K30: Ano 2 | L30: =+E34 | M30: =+M29+L30 | N30: =IF(M30>0,M30/L30*12)
A31: Custo médio ponderado capital = Rcp*CP%+Rca*(1-ti)*CA% (Rcp com BP 100%CP) | C31: =+C88 | D31: =+D88 | E31: =+E88 | F31: =+F88 | G31: =+G88 | H31: =+H88 | I31: =+H31 | K31: Ano 3 | L31: =+F34 | M31: =+M30+L31 | N31: =IF(M31>0,M31/L31*12)
A32: Fator de Atualização | C32: 1 | D32: =+C32*(1+D31) | E32: =+D32*(1+E31) | F32: =+E32*(1+F31) | G32: =+F32*(1+G31) | H32: =+G32*(1+H31) | I32: =+H32 | K32: Ano 4 | L32: =+G34 | M32: =+M31+L32 | N32: =IF(M32>0,M32/L32*12)
K33: Ano 5 | L33: =+H34 | M33: =+M32+L33 | N33: =IF(M33>0,M33/L33*12)
A34: Fluxos Atualizados | C34: =+C29/C32 | D34: =+D29/D32 | E34: =+E29/E32 | F34: =+F29/F32 | G34: =+G29/G32 | H34: =+H29/H32 | I34: =+I29/I32
A36: Fluxos Atualizados Acumulados | C36: =+C34 | D36: =+SUM($C$34:D34) | E36: =+SUM($C$34:E34) | F36: =+SUM($C$34:F34) | G36: =+SUM($C$34:G34) | H36: =+SUM($C$34:H34)+I34 | I36: *** | K36: Valor Residual ano N
K37: 1. PERPETUIDADE a crescer à taxa g em N+1 | N37: =($H$29*(1+Pressupostos!$B$38))/(Avaliação!$I$31-Pressupostos!$B$38)
A38: Valor Atual Líquido (VAL) | C38: =+I36 | K38: ou
K39: 2. (Ativo Cap Fixo não depreciado N + Fundo de Maneio Necessário N)/ Fator Atualiz. (h32*(1+I31)) | N39: =(+Balanço!$H$9+FundoManeio!$H$22)
A40: Taxa Interna de Rendibilidade | C40: =IRR(C29:I29,0.1)
A42: Pay Back Period (Arred. Ano Inteiro) | B42: Anos | C42: =COUNTIF(N28:N33,"falso") | D42: Meses | J42: Se versão excell for em inglês, meter na fórmula do Preríodo de Recuperação, o termo "false" em vez de "falso"
E43: Cálc. Manual
A47: Na Perspetiva do Investidor/accionista - Ótica do Cap. Próprio | C47: =+VN!C8 | D47: =+VN!D8 | E47: =+VN!E8 | F47: =+VN!F8 | G47: =+VN!G8 | H47: =+VN!H8 | I47: =H47+1 | L47: CF | M47: CF Acum
J48: ' + 1. ou + 2. Por defeito = 2. | K48: Ano 0 | L48: =+C54 | M48: =+L48 | N48: =IF(M48>0,M48/L48*12)
A49: Free Cash Flow do Equity = CF operac + CF investimento + CF financiamento | C49: =+'Cash Flow'!C21+PlanoFinanceiro!C12-PlanoFinanceiro!C23-DR!B28*(1-Pressupostos!$B$29) | D49: =+'Cash Flow'!D21+PlanoFinanceiro!D12-PlanoFinanceiro!D23-DR!C28*(1-Pressupostos!$B$29) | E49: =+'Cash Flow'!E21+PlanoFinanceiro!E12-PlanoFinanceiro!E23-DR!D28*(1-Pressupostos!$B$29) | F49: =+'Cash Flow'!F21+PlanoFinanceiro!F12-PlanoFinanceiro!F23-DR!E28*(1-Pressupostos!$B$29) | G49: =+'Cash Flow'!G21+PlanoFinanceiro!G12-PlanoFinanceiro!G23-DR!F28*(1-Pressupostos!$B$29) | H49: =+'Cash Flow'!H21+PlanoFinanceiro!H12-PlanoFinanceiro!H23-DR!G28*(1-Pressupostos!$B$29) | I49: =+N60 | K49: Ano 1 | L49: =+D54 | M49: =+M48+L49 | N49: =IF(M49>0,M49/L49*12)
K50: Ano 2 | L50: =+E54 | M50: =+M49+L50 | N50: =IF(M50>0,M50/L50*12)
A51: Taxa de Atualização = Rcp = Ru = RF+Bu*(Rm-Rf) | C51: =+C70 | D51: =+D70 | E51: =+E70 | F51: =+F70 | G51: =+G70 | H51: =+H70 | I51: =+I70 | K51: Ano 3 | L51: =+F54 | M51: =+M50+L51 | N51: =IF(M51>0,M51/L51*12)
A52: Fator de Atualização | C52: 1 | D52: =+C52*(1+D51) | E52: =+D52*(1+E51) | F52: =+E52*(1+F51) | G52: =+F52*(1+G51) | H52: =+G52*(1+H51) | I52: =+H52 | K52: Ano 4 | L52: =+G54 | M52: =+M51+L52 | N52: =IF(M52>0,M52/L52*12)
K53: Ano 5 | L53: =+H54 | M53: =+M52+L53 | N53: =IF(M53>0,M53/L53*12)
A54: Fluxos Atualizados | C54: =+C49/C52 | D54: =+D49/D52 | E54: =+E49/E52 | F54: =+F49/F52 | G54: =+G49/G52 | H54: =+H49/H52 | I54: =+I49/I52
A56: Fluxos Atualizados Acumulados | C56: =+C54 | D56: =+SUM($C$54:D54) | E56: =+SUM($C$54:E54) | F56: =+SUM($C$54:F54) | G56: =+SUM($C$54:G54) | H56: =+SUM($C$54:H54) | I56: =+SUM($C$54:I54)
K57: Valor Residual ano N
A58: Valor Atual Líquido (VAL) | C58: =I56 | E58: Valor Residual = Cap. Próprio no último ano | K58: 1. PERPETUIDADE a crescer à taxa g | N58: =+($H$49*(1+Pressupostos!$B$38))/($I$51-Pressupostos!$B$38)
K59: ou
A60: Taxa Interna de Rendibilidade | C60: =IRR(C49:I49,0.1) | K60: 2. Cap Próprio N [ou (Ativo não depreciado + F.Maneio -Passivo) ]/ (h54*(1+I53)) | N60: =+Balanço!H33/(H52*(1+I51))
A62: Pay Back Period (Arred. Ano Inteiro) | B62: Anos | C62: =COUNTIF(N48:N53,"falso") | D62: Meses
E63: Cálc. Manual | J63: Se versão excell for em inglês, meter na fórmula do Preríodo de Recuperação, o termo "false" em vez de "falso"
A66: TAXAS DE ATUALIZAÇÃO
A67: Custo do capital próprio (CAPM) = Rcp = Rf + Bu*(Rm-Rf)
A68: Taxa de Juro de Ativos Sem Risco | C68: =+Pressupostos!B35 | D68: =+C68*(1+VN!D$9) | E68: =+D68*(1+VN!E$9) | F68: =+E68*(1+VN!F$9) | G68: =+F68*(1+VN!G$9) | H68: =+G68*(1+VN!H$9) | I68: =+H68
A69: Prémio de Risco de Mercado | C69: =+Pressupostos!B36 | D69: =+C69 | E69: =+D69 | F69: =+E69 | G69: =+F69 | H69: =+G69 | I69: =+H69
A70: Taxa de Atualização Rcp = Rf + Bu*(Rm-Rf) com Bu | C70: =+C68+Pressupostos!$B$37*(Avaliação!C69) | D70: =+D68+Pressupostos!$B$37*(Avaliação!D69) | E70: =+E68+Pressupostos!$B$37*(Avaliação!E69) | F70: =+F68+Pressupostos!$B$37*(Avaliação!F69) | G70: =+G68+Pressupostos!$B$37*(Avaliação!G69) | H70: =+H68+Pressupostos!$B$37*(Avaliação!H69) | I70: =+H70
A71: Fator de Atualização | C71: 1 | D71: =+C71*(1+D70) | E71: =+D71*(1+E70) | F71: =+E71*(1+F70) | G71: =+F71*(1+G70) | H71: =+G71*(1+H70) | I71: -
A72: Financiamento
A73: Custo Financiamento j | C73: =+Pressupostos!$B$33 | D73: =+Pressupostos!$B$33 | E73: =+Pressupostos!$B$33 | F73: =+Pressupostos!$B$33 | G73: =+Pressupostos!$B$33 | H73: =+Pressupostos!$B$33
A74: Custo Financiamento com Efeito Fiscal (1-t)*j | C74: =C73*(1-Pressupostos!$B$29) | D74: =D73*(1-Pressupostos!$B$29) | E74: =E73*(1-Pressupostos!$B$29) | F74: =F73*(1-Pressupostos!$B$29) | G74: =G73*(1-Pressupostos!$B$29) | H74: =H73*(1-Pressupostos!$B$29)
A76: Cálculo do CMPCP (wacc) (ótica do investimento)
A77: ESTRUTURA DO FINANCIAMENTO DO PROJETO | B77: Ano 0 - Sem atividade* | C77: =+C27 | D77: =+C77+1 | E77: =+D77+1 | F77: =+E77+1 | G77: =+F77+1 | H77: =+G77+1
A78: Passivo Remunerado | B78: =+Financiamento!C18 | C78: =IF(DR!$B$8>0,Avaliação!B78,+Balanço!C39+Balanço!C46) | D78: =Balanço!D39+Balanço!D46 | E78: =Balanço!E39+Balanço!E46 | F78: =Balanço!F39+Balanço!F46 | G78: =Balanço!G39+Balanço!G46 | H78: =Balanço!H39+Balanço!H46
A79: Capital Próprio | B79: =+Financiamento!C15+Financiamento!C16 | C79: =IF(DR!$B$8>0,Avaliação!B79,+Balanço!C33) | D79: =+Balanço!D33 | E79: =+Balanço!E33 | F79: =+Balanço!F33 | G79: =+Balanço!G33 | H79: =+Balanço!H33
A80: TOTAL | B80: =SUM(B78:B79) | C80: =+C78+C79 | D80: =+D78+D79 | E80: =+E78+E79 | F80: =+F78+F79 | G80: =+G78+G79 | H80: =+H78+H79
A81: % Passivo Remunerado | C81: =+C78/C$80 | D81: =+D78/D80 | E81: =+E78/E80 | F81: =+F78/F80 | G81: =+G78/G80 | H81: =+H78/H80
A82: % Capital Próprio | C82: =+C79/C$80 | D82: =+D79/D80 | E82: =+E79/E80 | F82: =+F79/F80 | G82: =+G79/G80 | H82: =+H79/H80
B83: * Se há atividade no ano inicial, considerar a estrutura inicial de financiamento
A85: CMPCP (wacc) (ótica do investimento) = Rcp*CP%+Rca*(1-ti)*CA% (Rcp com Bu) (=Bp otica 100% cap próprio)
A86: Rcp = Rf+Bu*(Rm-Rf) | C86: =+C70 | D86: =+D70 | E86: =+E70 | F86: =+F70 | G86: =+G70 | H86: =+H70 | I86: =+I70
A87: Custo do Financiamento Líquido = (1-t)*j | C87: =+C74 | D87: =+D74 | E87: =+E74 | F87: =+F74 | G87: =+G74 | H87: =+H74 | I87: =+H87
A88: cmpcp com cash flows líquidos de financiamento Rcp*CP%+Rca*(1-ti)*CA% | C88: =+C86*C82+C87*C81 | D88: =+D86*D82+D87*D81 | E88: =+E86*E82+E87*E81 | F88: =+F86*F82+F87*F81 | G88: =+G86*G82+G87*G81 | H88: =+H86*H82+H87*H81 | I88: =+H88
A90: CMPCP (wacc) (ótica do investimento) = Rcp*CP%+Rca*(1-ti)*CA% (Rcp com Bp - Beta do projeto) | I90: Não utilizado
A91: Beta p = Bu * (1+(1-t)*CA/CP) para cálc. alternativo | C91: =+Pressupostos!$B37*(1+(1-Pressupostos!$B29)*(Avaliação!C78/Avaliação!C79)) | D91: =+Pressupostos!$B37*(1+(1-Pressupostos!$B29)*(Avaliação!D78/Avaliação!D79)) | E91: =+Pressupostos!$B37*(1+(1-Pressupostos!$B29)*(Avaliação!E78/Avaliação!E79)) | F91: =+Pressupostos!$B37*(1+(1-Pressupostos!$B29)*(Avaliação!F78/Avaliação!F79)) | G91: =+Pressupostos!$B37*(1+(1-Pressupostos!$B29)*(Avaliação!G78/Avaliação!G79)) | H91: =+Pressupostos!$B37*(1+(1-Pressupostos!$B29)*(Avaliação!H78/Avaliação!H79))
C92: Considera-se Bu = Bu ano inicial, não influenciado por oscilações sucessivas da estrutura de capital
A93: Custo Capital Rcp = Rf+Bp*(Rm-Rf) | C93: =(C68+(C91*C69)) | D93: =(D68+(D91*D69)) | E93: =(E68+(E91*E69)) | F93: =(F68+(F91*F69)) | G93: =(G68+(G91*G69)) | H93: =(H68+(H91*H69))
A94: Custo Médio Ponderado do Capital (wacc) = Rcp*CP% + j*(1-t)*CA% | C94: =(C81*C74)+(C82*C93) | D94: =(D81*D74)+(D82*D93) | E94: =(E81*E74)+(E82*E93) | F94: =(F81*F74)+(F82*F93) | G94: =(G81*G74)+(G82*G93) | H94: =(H81*H74)+(H82*H93)
D95: Considera-se wacc t = wacc 0 u ano inicial, não influenciado por oscilações sucessivas da estrutura de capital

Sheet Calculos Auxil- livre
G1: Empresa: | H1: =+Pressupostos!E1
A4: Cálculos Auxiliares
A6: Consumo de Unidades de Matérias-Primas por Unidade de Produto Acabado
A7: Matérias-Primas e Subsidiárias (Discriminação) | B7: Unidade de Medida | C7: Produto A | D7: Produto B | E7: Produto C | F7: Produto D
A24: Produção (em Quantidades) | H24: Unidades físicas
A25: Produtos | C25: =+Pressupostos!B11 | D25: =+C25+1 | E25: =+D25+1 | F25: =+E25+1 | G25: =+F25+1 | H25: =+G25+1
A26: Produto A
A27: Produto B
A28: Produto C
A29: Produto D
A33: TOTAL | C33: =+SUM(C26:C32) | D33: =+SUM(D26:D32) | E33: =+SUM(E26:E32) | F33: =+SUM(F26:F32) | G33: =+SUM(G26:G32) | H33: =+SUM(H26:H32)
A35: Consumo de Matérias-Primas 1* | H35: Unidades Físicas
A36: Matérias-Primas e Subsidiárias | C36: =+C25 | D36: =+D25 | E36: =+E25 | F36: =+F25 | G36: =+G25 | H36: =+H25
A53: Preço das Matérias-Primas e Subsidiárias
A54: Matérias-Primas e Subsidiárias | C54: =+C36 | D54: =+D36 | E54: =+E36 | F54: =+F36 | G54: =+G36 | H54: =+H36
A71: Valor do consumo 2*
A72: Matérias-Primas e Subsidiárias | C72: =+C25 | D72: =+D25 | E72: =+E25 | F72: =+F25 | G72: =+G25 | H72: =+H25
C73: =+C37*C55 | D73: =+D37*D55 | E73: =+E37*E55 | F73: =+F37*F55 | G73: =+G37*G55 | H73: =+H37*H55
C74: =+C38*C56 | D74: =+D38*D56 | E74: =+E38*E56 | F74: =+F38*F56 | G74: =+G38*G56 | H74: =+H38*H56
C75: =+C39*C57 | D75: =+D39*D57 | E75: =+E39*E57 | F75: =+F39*F57 | G75: =+G39*G57 | H75: =+H39*H57
C76: =+C40*C58 | D76: =+D40*D58 | E76: =+E40*E58 | F76: =+F40*F58 | G76: =+G40*G58 | H76: =+H40*H58
C77: =+C41*C59 | D77: =+D41*D59 | E77: =+E41*E59 | F77: =+F41*F59 | G77: =+G41*G59 | H77: =+H41*H59
C78: =+C42*C60 | D78: =+D42*D60 | E78: =+E42*E60 | F78: =+F42*F60 | G78: =+G42*G60 | H78: =+H42*H60
C79: =+C43*C61 | D79: =+D43*D61 | E79: =+E43*E61 | F79: =+F43*F61 | G79: =+G43*G61 | H79: =+H43*H61
C80: =+C44*C62 | D80: =+D44*D62 | E80: =+E44*E62 | F80: =+F44*F62 | G80: =+G44*G62 | H80: =+H44*H62
C81: =+C45*C63 | D81: =+D45*D63 | E81: =+E45*E63 | F81: =+F45*F63 | G81: =+G45*G63 | H81: =+H45*H63
C82: =+C46*C64 | D82: =+D46*D64 | E82: =+E46*E64 | F82: =+F46*F64 | G82: =+G46*G64 | H82: =+H46*H64
C83: =+C47*C65 | D83: =+D47*D65 | E83: =+E47*E65 | F83: =+F47*F65 | G83: =+G47*G65 | H83: =+H47*H65
C84: =+C48*C66 | D84: =+D48*D66 | E84: =+E48*E66 | F84: =+F48*F66 | G84: =+G48*G66 | H84: =+H48*H66
... C86: =+C50*C68 | D86: =+D50*D68 | E86: =+E50*E68 | F86: =+F50*F68 | G86: =+G50*G68 | H86: =+H50*H68
A87: TOTAL | C87: =+SUM(C73:C86) | D87: =+SUM(D73:D86) | E87: =+SUM(E73:E86) | F87: =+SUM(F73:F86) | G87: =+SUM(G73:G86) | H87: =+SUM(H73:H86)
A90: 1* Obtido da multiplicação da produção pelo consumo de matéria-prima por unidade de produto acabado.
A91: 2* Obtido da multiplicação do consumo das matérias-primas pelo preço.

Sheet F livre
B1: VALOR RESIDUAL
B2: SENSIBILIDADE
B3: SIMULAÇÃO
B5: Base
C7: Qv | D7: Preço | E7: Custo ?? | F7: VAL | G7: TIR | H7: PR
B8: BASE | C8: 1
B9: Variação | C9: -0.1
B10: Variação
B11: Variação
B12: Variação
B13: Variação
B14: Variação
H19: =10/17.5 | I19: =20/27.5
